Workbook

Sheet Comparación
A1: CÓDIGO | B1: DESCRIPCIÓN | C1: UNIDAD | D1: CUOTA_DICTAMEN | H1: CÓDIGO | I1: DESCRIPCIÓN | J1: UNIDAD | K1: CUOTA_DICTAMEN
A2: 3303.00.01 | B2: Aguas de tocador. | C2: L | D2: 25 | E2: =VLOOKUP(A2,$H$2:$K$1464,4,FALSE) -> 25 | F2: =IF(D2=E2,"") | H2: 3303.00.01 | I2: Aguas de tocador. | J2: L | K2: 25 | L2: =VLOOKUP(H2,$A$2:$D$1464,4,FALSE) -> 25 | M2: =IF(K2=L2,"",)
A3: 3303.00.99 | B3: Los demás. | C3: L | D3: 25 | E3: =VLOOKUP(A3,$H$2:$K$1464,4,FALSE) -> 25 | F3: =IF(D3=E3,"") | H3: 3303.00.99 | I3: Los demás. | J3: L | K3: 25 | L3: =VLOOKUP(H3,$A$2:$D$1464,4,FALSE) -> 25 | M3: =IF(K3=L3,"",)
A4: 3304.10.01 | B4: Preparaciones para el maquillaje de los labios. | C4: Kg | D4: 36 | E4: =VLOOKUP(A4,$H$2:$K$1464,4,FALSE) -> 36 | F4: =IF(D4=E4,"") | H4: 3304.10.01 | I4: Preparaciones para el maquillaje de los labios. | J4: Kg | K4: 36 | L4: =VLOOKUP(H4,$A$2:$D$1464,4,FALSE) -> 36 | M4: =IF(K4=L4,"",)
A5: 3304.20.01 | B5: Preparaciones para el maquillaje de los ojos. | C5: Kg | D5: 25 | E5: =VLOOKUP(A5,$H$2:$K$1464,4,FALSE) -> 25 | F5: =IF(D5=E5,"") | H5: 3304.20.01 | I5: Preparaciones para el maquillaje de los ojos. | J5: Kg | K5: 25 | L5: =VLOOKUP(H5,$A$2:$D$1464,4,FALSE) -> 25 | M5: =IF(K5=L5,"",)
A6: 3304.30.01 | B6: Preparaciones para manicuras o pedicuros. | C6: Kg | D6: 25 | E6: =VLOOKUP(A6,$H$2:$K$1464,4,FALSE) -> 25 | F6: =IF(D6=E6,"") | H6: 3304.30.01 | I6: Preparaciones para manicuras o pedicuros. | J6: Kg | K6: 25 | L6: =VLOOKUP(H6,$A$2:$D$1464,4,FALSE) -> 25 | M6: =IF(K6=L6,"",)
A7: 3304.91.01 | B7: Polvos, incluidos los compactos. | C7: Kg | D7: 25 | E7: =VLOOKUP(A7,$H$2:$K$1464,4,FALSE) -> 25 | F7: =IF(D7=E7,"") | H7: 3304.91.01 | I7: Polvos, incluidos los compactos. | J7: Kg | K7: 25 | L7: =VLOOKUP(H7,$A$2:$D$1464,4,FALSE) -> 25 | M7: =IF(K7=L7,"",)
A8: 3304.99.01 | B8: Leches cutáneas. | C8: Kg | D8: 25 | E8: =VLOOKUP(A8,$H$2:$K$1464,4,FALSE) -> 25 | F8: =IF(D8=E8,"") | H8: 3304.99.01 | I8: Leches cutáneas. | J8: Kg | K8: 25 | L8: =VLOOKUP(H8,$A$2:$D$1464,4,FALSE) -> 25 | M8: =IF(K8=L8,"",)
A9: 3304.99.99 | B9: Las demás. | C9: Kg | D9: 25 | E9: =VLOOKUP(A9,$H$2:$K$1464,4,FALSE) -> 25 | F9: =IF(D9=E9,"") | H9: 3304.99.99 | I9: Las demás. | J9: Kg | K9: 25 | L9: =VLOOKUP(H9,$A$2:$D$1464,4,FALSE) -> 25 | M9: =IF(K9=L9,"",)
A10: 3305.10.01 | B10: Champúes. | C10: Kg | D10: 25 | E10: =VLOOKUP(A10,$H$2:$K$1464,4,FALSE) -> 25 | F10: =IF(D10=E10,"") | H10: 3305.10.01 | I10: Champúes. | J10: Kg | K10: 25 | L10: =VLOOKUP(H10,$A$2:$D$1464,4,FALSE) -> 25 | M10: =IF(K10=L10,"",)
A11: 3305.20.01 | B11: Preparaciones para ondulación o desrizado permanentes. | C11: Kg | D11: 25 | E11: =VLOOKUP(A11,$H$2:$K$1464,4,FALSE) -> 25 | F11: =IF(D11=E11,"") | H11: 3305.20.01 | I11: Preparaciones para ondulación o desrizado permanentes | J11: Kg | K11: 25 | L11: =VLOOKUP(H11,$A$2:$D$1464,4,FALSE) -> 25 | M11: =IF(K11=L11,"",)
A12: 3305.30.01 | B12: Lacas para el cabello. | C12: Kg | D12: 25 | E12: =VLOOKUP(A12,$H$2:$K$1464,4,FALSE) -> 25 | F12: =IF(D12=E12,"") | H12: 3305.30.01 | I12: Lacas para el cabello | J12: Kg | K12: 25 | L12: =VLOOKUP(H12,$A$2:$D$1464,4,FALSE) -> 25 | M12: =IF(K12=L12,"",)
A13: 3305.90.99 | B13: Las demás. | C13: Kg | D13: 25 | E13: =VLOOKUP(A13,$H$2:$K$1464,4,FALSE) -> 25 | F13: =IF(D13=E13,"") | H13: 3305.90.99 | I13: Las demás | J13: Kg | K13: 25 | L13: =VLOOKUP(H13,$A$2:$D$1464,4,FALSE) -> 25 | M13: =IF(K13=L13,"",)
... A1109: 7226.19.99 | B1109: Los demás. | C1109: Kg | D1109: 35 | E1109: =VLOOKUP(A1109,$H$2:$K$1464,4,FALSE) -> 35 | F1109: =IF(D1109=E1109,"") | H1109: 7226.19.99 | I1109: Los demás. | J1109: Kg | K1109: 35 | L1109: =VLOOKUP(H1109,$A$2:$D$1464,4,FALSE) -> 35 | M1109: =IF(K1109=L1109,"",)
A1110: 7226.20.01 | B1110: De acero rápido. | C1110: Kg | D1110: Ex. | E1110: =VLOOKUP(A1110,$H$2:$K$1464,4,FALSE) -> Ex. | F1110: =IF(D1110=E1110,"") | H1110: 7226.20.01 | I1110: De acero rápido. | J1110: Kg | K1110: Ex. | L1110: =VLOOKUP(H1110,$A$2:$D$1464,4,FALSE) -> Ex. | M1110: =IF(K1110=L1110,"",)
A1111: 7226.91.07 | B1111: Simplemente laminados en caliente. | C1111: Kg | D1111: 35 | E1111: =VLOOKUP(A1111,$H$2:$K$1464,4,FALSE) -> 35 | F1111: =IF(D1111=E1111,"") | H1111: 7226.91.07 | I1111: Simplemente laminados en caliente | J1111: Kg | K1111: 35 | L1111: =VLOOKUP(H1111,$A$2:$D$1464,4,FALSE) -> 35 | M1111: =IF(K1111=L1111,"",)
A1112: 7226.92.06 | B1112: Simplemente laminados en frío. | C1112: Kg | D1112: 35 | E1112: =VLOOKUP(A1112,$H$2:$K$1464,4,FALSE) -> 35 | F1112: =IF(D1112=E1112,"") | H1112: 7226.92.06 | I1112: Simplemente laminados en frío. | J1112: Kg | K1112: 35 | L1112: =VLOOKUP(H1112,$A$2:$D$1464,4,FALSE) -> 35 | M1112: =IF(K1112=L1112,"",)
A1113: 7226.99.99 | B1113: Los demás. | C1113: Kg | D1113: 35 | E1113: =VLOOKUP(A1113,$H$2:$K$1464,4,FALSE) -> 35 | F1113: =IF(D1113=E1113,"") | H1113: 7226.99.99 | I1113: Los demás | J1113: Kg | K1113: 35 | L1113: =VLOOKUP(H1113,$A$2:$D$1464,4,FALSE) -> 35 | M1113: =IF(K1113=L1113,"",)
A1114: 7227.10.01 | B1114: De acero rápido. | C1114: Kg | D1114: 35 | E1114: =VLOOKUP(A1114,$H$2:$K$1464,4,FALSE) -> 35 | F1114: =IF(D1114=E1114,"") | H1114: 7227.10.01 | I1114: De acero rápido. | J1114: Kg | K1114: 35 | L1114: =VLOOKUP(H1114,$A$2:$D$1464,4,FALSE) -> 35 | M1114: =IF(K1114=L1114,"",)
A1115: 7227.20.01 | B1115: De acero silicomanganeso. | C1115: Kg | D1115: 35 | E1115: =VLOOKUP(A1115,$H$2:$K$1464,4,FALSE) -> 35 | F1115: =IF(D1115=E1115,"") | H1115: 7227.20.01 | I1115: De acero silicomanganeso. | J1115: Kg | K1115: 35 | L1115: =VLOOKUP(H1115,$A$2:$D$1464,4,FALSE) -> 35 | M1115: =IF(K1115=L1115,"",)
A1116: 7227.90.99 | B1116: Los demás. | C1116: Kg | D1116: 35 | E1116: =VLOOKUP(A1116,$H$2:$K$1464,4,FALSE) -> 35 | F1116: =IF(D1116=E1116,"") | H1116: 7227.90.99 | I1116: Los demás. | J1116: Kg | K1116: 35 | L1116: =VLOOKUP(H1116,$A$2:$D$1464,4,FALSE) -> 35 | M1116: =IF(K1116=L1116,"",)
A1117: 7228.10.02 | B1117: Barras de acero rápido. | C1117: Kg | D1117: 35 | E1117: =VLOOKUP(A1117,$H$2:$K$1464,4,FALSE) -> 35 | F1117: =IF(D1117=E1117,"") | H1117: 7228.10.02 | I1117: Barras de acero rápido. | J1117: Kg | K1117: 35 | L1117: =VLOOKUP(H1117,$A$2:$D$1464,4,FALSE) -> 35 | M1117: =IF(K1117=L1117,"",)
A1118: 7228.20.02 | B1118: Barras de acero silicomanganeso. | C1118: Kg | D1118: 35 | E1118: =VLOOKUP(A1118,$H$2:$K$1464,4,FALSE) -> 35 | F1118: =IF(D1118=E1118,"") | H1118: 7228.20.02 | I1118: Barras de acero silicomanganeso | J1118: Kg | K1118: 35 | L1118: =VLOOKUP(H1118,$A$2:$D$1464,4,FALSE) -> 35 | M1118: =IF(K1118=L1118,"",)
A1119: 7228.30.99 | B1119: Las demás. | C1119: Kg | D1119: 35 | E1119: =VLOOKUP(A1119,$H$2:$K$1464,4,FALSE) -> 35 | F1119: =IF(D1119=E1119,"") | H1119: 7228.30.99 | I1119: Las demás. | J1119: Kg | K1119: 35 | L1119: =VLOOKUP(H1119,$A$2:$D$1464,4,FALSE) -> 35 | M1119: =IF(K1119=L1119,"",)
A1120: 7228.40.91 | B1120: Las demás barras, simplemente forjadas. | C1120: Kg | D1120: 35 | E1120: =VLOOKUP(A1120,$H$2:$K$1464,4,FALSE) -> 35 | F1120: =IF(D1120=E1120,"") | H1120: 7228.40.91 | I1120: Las demás barras, simplemente forjadas. | J1120: Kg | K1120: 35 | L1120: =VLOOKUP(H1120,$A$2:$D$1464,4,FALSE) -> 35 | M1120: =IF(K1120=L1120,"",)
A1121: 7228.50.91 | B1121: Las demás barras, simplemente obtenidas o acabadas en frío. | C1121: Kg | D1121: 35 | E1121: =VLOOKUP(A1121,$H$2:$K$1464,4,FALSE) -> 35 | F1121: =IF(D1121=E1121,"") | H1121: 7228.50.91 | I1121: Las demás barras, simplemente obtenidas o acabadas en frío. | J1121: Kg | K1121: 35 | L1121: =VLOOKUP(H1121,$A$2:$D$1464,4,FALSE) -> 35 | M1121: =IF(K1121=L1121,"",)
A1122: 7228.60.91 | B1122: Las demás barras. | C1122: Kg | D1122: 35 | E1122: =VLOOKUP(A1122,$H$2:$K$1464,4,FALSE) -> 35 | F1122: =IF(D1122=E1122,"") | H1122: 7228.60.91 | I1122: Las demás barras. | J1122: Kg | K1122: 35 | L1122: =VLOOKUP(H1122,$A$2:$D$1464,4,FALSE) -> 35 | M1122: =IF(K1122=L1122,"",)
... A1129: 7302.10.02 | B1129: Carriles (rieles). | C1129: Kg | D1129: 20 | E1129: =VLOOKUP(A1129,$H$2:$K$1464,4,FALSE) -> 20 | F1129: =IF(D1129=E1129,"") | H1129: 7302.10.02 | I1129: Carriles (rieles). | J1129: Kg | K1129: 20 | L1129: =VLOOKUP(H1129,$A$2:$D$1464,4,FALSE) -> 20 | M1129: =IF(K1129=L1129,"",)
A1130: 7302.40.02 | B1130: Bridas y placas de asiento. | C1130: Kg | D1130: Ex. | E1130: =VLOOKUP(A1130,$H$2:$K$1464,4,FALSE) -> Ex. | F1130: =IF(D1130=E1130,"") | H1130: 7302.40.02 | I1130: Bridas y placas de asiento. | J1130: Kg | K1130: Ex. | L1130: =VLOOKUP(H1130,$A$2:$D$1464,4,FALSE) -> Ex. | M1130: =IF(K1130=L1130,"",)
A1131: 7303.00.02 | B1131: Tubos y perfiles huecos, de fundición. | C1131: Kg | D1131: 35 | E1131: =VLOOKUP(A1131,$H$2:$K$1464,4,FALSE) -> 35 | F1131: =IF(D1131=E1131,"") | H1131: 7303.00.02 | I1131: Tubos y perfiles huecos, de fundición | J1131: Kg | K1131: 35 | L1131: =VLOOKUP(H1131,$A$2:$D$1464,4,FALSE) -> 35 | M1131: =IF(K1131=L1131,"",)
A1132: 7304.11.01 | B1132: Tubos laminados en caliente, sin recubrimiento u otros trabajos de superficie, incluidos los tubos laminados en caliente barnizados o laqueados: de diámetro exterior inferior o igual a 114.3 mm y espesor de pared superior o igual a 4 mm sin exceder de 19.5 mm. | C1132: Kg | D1132: 35 | E1132: =VLOOKUP(A1132,$H$2:$K$1464,4,FALSE) -> 35 | F1132: =IF(D1132=E1132,"") | H1132: 7304.11.01 | I1132: Tubos laminados en caliente, sin recubrimiento u otros trabajos de superficie, incluidos los tubos laminados en caliente o laqueados: de diámetro exterior inferior o igual a 114.3 mm y espesor de pared superior o igual a 4 mm sin exceder de 19.5 mm. | J1132: Kg | K1132: 35 | L1132: =VLOOKUP(H1132,$A$2:$D$1464,4,FALSE) -> 35 | M1132: =IF(K1132=L1132,"",)
A1133: 7304.11.02 | B1133: Tubos laminados en caliente, sin recubrimiento u otros trabajos de superficie, incluidos los tubos laminados en caliente barnizados o laqueados: de diámetro exterior superior a 114.3 mm sin exceder de 406.4 mm y espesor de pared superior o igual a 6.35 mm sin exceder de 38.1 mm. | C1133: Kg | D1133: 35 | E1133: =VLOOKUP(A1133,$H$2:$K$1464,4,FALSE) -> 35 | F1133: =IF(D1133=E1133,"") | H1133: 7304.11.02 | I1133: Tubos laminados en caliente, sin recubrimiento u otros trabajos de superficie, incluidos los tubos laminados en caliente barnizados o laqueados: de diámetro exterior superior a 114.3 mm sin exceder de 406.4 mm y espesor de pared superior o igual a 6.35 mm sin exceder de 38.1 mm. | J1133: Kg | K1133: 35 | L1133: =VLOOKUP(H1133,$A$2:$D$1464,4,FALSE) -> 35 | M1133: =IF(K1133=L1133,"",)
A1134: 7304.11.03 | B1134: Tubos laminados en caliente, sin recubrimiento u otros trabajos de superficie, incluidos los tubos laminados en caliente barnizados o laqueados: de diámetro exterior superior a 406.4 mm y espesor de pared superior o igual a 9.52 mm sin exceder de 31.75 mm. | C1134: Kg | D1134: 35 | E1134: =VLOOKUP(A1134,$H$2:$K$1464,4,FALSE) -> 35 | F1134: =IF(D1134=E1134,"") | H1134: 7304.11.03 | I1134: Tubos laminados en caliente, sin recubrimiento u otros trabajos de superficie, incluidos los tubos laminados en caliente barnizados o laqueados: de diámetro exterior superior a 406.4 mm y espesor de pared superior o igual a 9.52 mm sin exceder de 31.75 mm. | J1134: Kg | K1134: 35 | L1134: =VLOOKUP(H1134,$A$2:$D$1464,4,FALSE) -> 35 | M1134: =IF(K1134=L1134,"",)
A1135: 7304.11.04 | B1135: Tubos laminados en frío, sin recubrimiento u otros trabajos de superficie, incluidos los tubos laminados en frío barnizados o laqueados: de diámetro exterior inferior o igual a 114.3 mm y espesor de pared superior o igual a 1.27 mm sin exceder de 9.5 mm. | C1135: Kg | D1135: 35 | E1135: =VLOOKUP(A1135,$H$2:$K$1464,4,FALSE) -> 35 | F1135: =IF(D1135=E1135,"") | H1135: 7304.11.04 | I1135: Tubos laminados en frío, sin recubrimiento u otros trabajos de superficie, incluidos los tubos laminados en frío barnizados o laqueados: de diámetro exterior inferior o igual a 114.3mm y espesor de pared superior o igual a 1.27 mm sin exceder de 9.5 mm. | J1135: Kg | K1135: 35 | L1135: =VLOOKUP(H1135,$A$2:$D$1464,4,FALSE) -> 35 | M1135: =IF(K1135=L1135,"",)
A1136: 7304.11.99 | B1136: Los demás. | C1136: Kg | D1136: 35 | E1136: =VLOOKUP(A1136,$H$2:$K$1464,4,FALSE) -> 35 | F1136: =IF(D1136=E1136,"") | H1136: 7304.11.99 | I1136: Los demás. | J1136: Kg | K1136: 35 | L1136: =VLOOKUP(H1136,$A$2:$D$1464,4,FALSE) -> 35 | M1136: =IF(K1136=L1136,"",)
A1137: 7304.19.01 | B1137: Tubos laminados en caliente, sin recubrimiento u otros trabajos de superficie, incluidos los tubos laminados en caliente barnizados o laqueados: de diámetro exterior inferior o igual a 114.3 mm y espesor de pared superior o igual a 4 mm sin exceder de 19.5 mm. | C1137: Kg | D1137: 35 | E1137: =VLOOKUP(A1137,$H$2:$K$1464,4,FALSE) -> 35 | F1137: =IF(D1137=E1137,"") | H1137: 7304.19.01 | I1137: Tubos laminados en caliente, sin recubrimiento u otros trabajos de superficie, incluidos los tubos laminados en caliente barnizados o laqueados: de diámetro exterior inferior o igual a 114.3mm y espesor de pared superior o igual a 4mm sin exceder de 19.5 mm. | J1137: Kg | K1137: 35 | L1137: =VLOOKUP(H1137,$A$2:$D$1464,4,FALSE) -> 35 | M1137: =IF(K1137=L1137,"",)
A1138: 7304.19.02 | B1138: Tubos laminados en caliente, sin recubrimiento u otros trabajos de superficie, incluidos los tubos laminados en caliente barnizados o laqueados: de diámetro exterior superior a 114.3 mm sin exceder de 406.4 mm y espesor de pared superior o igual a 6.35 mm sin exceder de 38.1 mm. | C1138: Kg | D1138: 35 | E1138: =VLOOKUP(A1138,$H$2:$K$1464,4,FALSE) -> 35 | F1138: =IF(D1138=E1138,"") | H1138: 7304.19.02 | I1138: Tubos laminados en caliente, sin recubrimiento u otros trabajos de superficie, incluidos los tubos laminados en caliente barnizados o laqueados: de diámetro exterior superior a 114.3 mm sin exceder de 406.4 mm y espesor de pared superior o igual a 6.35 mm sin exceder de 38.1 mm. | J1138: Kg | K1138: 35 | L1138: =VLOOKUP(H1138,$A$2:$D$1464,4,FALSE) -> 35 | M1138: =IF(K1138=L1138,"",)
A1139: 7304.19.04 | B1139: Tubos laminados en frío, sin recubrimiento u otros trabajos de superficie, incluidos los tubos laminados en frío barnizados o laqueados: de diámetro exterior inferior o igual a 114.3 mm y espesor de pared superior o igual a 1.27 mm sin exceder de 9.5 mm. | C1139: Kg | D1139: 35 | E1139: =VLOOKUP(A1139,$H$2:$K$1464,4,FALSE) -> 35 | F1139: =IF(D1139=E1139,"") | H1139: 7304.19.04 | I1139: Tubos laminados en frío, sin recubrimiento u otros trabajos de superficie, incluidos los tubos laminados en frío barnizados o laqueados: de diámetro exterior inferior o igual a 114.3 mm y espesor | J1139: Kg | K1139: 35 | L1139: =VLOOKUP(H1139,$A$2:$D$1464,4,FALSE) -> 35 | M1139: =IF(K1139=L1139,"",)
A1140: 7304.19.05 | B1140: Tubos semiterminados o esbozos para uso exclusivo de empresas fabricantes de tubería estirada en frío. | C1140: Kg | D1140: 35 | E1140: =VLOOKUP(A1140,$H$2:$K$1464,4,FALSE) -> 35 | F1140: =IF(D1140=E1140,"") | H1140: 7304.19.05 | I1140: Tubos semiterminados o esbozos para exclusivo de empresas fabricantes de tubería estirada en frío | J1140: Kg | K1140: 35 | L1140: =VLOOKUP(H1140,$A$2:$D$1464,4,FALSE) -> 35 | M1140: =IF(K1140=L1140,"",)
A1141: 7304.19.99 | B1141: Los demás. | C1141: Kg | D1141: 35 | E1141: =VLOOKUP(A1141,$H$2:$K$1464,4,FALSE) -> 35 | F1141: =IF(D1141=E1141,"") | H1141: 7304.19.99 | I1141: Los demás | J1141: Kg | K1141: 35 | L1141: =VLOOKUP(H1141,$A$2:$D$1464,4,FALSE) -> 35 | M1141: =IF(K1141=L1141,"",)
A1142: 7304.24.91 | B1142: Los demás, de acero inoxidable. | C1142: Kg | D1142: 35 | E1142: =VLOOKUP(A1142,$H$2:$K$1464,4,FALSE) -> 35 | F1142: =IF(D1142=E1142,"") | H1142: 7304.24.91 | I1142: Los demás, de acero inoxidable | J1142: Kg | K1142: 35 | L1142: =VLOOKUP(H1142,$A$2:$D$1464,4,FALSE) -> 35 | M1142: =IF(K1142=L1142,"",)
... A1464: 9619.00.03 | B1464: Pañales y artículos similares, de otras materias textiles, excepto lo comprendido en la fracción arancelaria 9619.00.02. | C1464: Pza | D1464: 35 | E1464: =VLOOKUP(A1464,$H$2:$K$1464,4,FALSE) -> 35 | F1464: =IF(D1464=E1464,"") | H1464: 9619.00.03 | I1464: Pañales y artículos similares, de otras materias textiles, excepto lo comprendido en la fracción arancelaria 9619.00.02 | J1464: Pza | K1464: 35 | L1464: =VLOOKUP(H1464,$A$2:$D$1464,4,FALSE) -> 35 | M1464: =IF(K1464=L1464,"",)

Sheet LIGIE Diciembre DOF
A1: DOF 29/12/2025 | F1: Códigos Mantenidos | K1: Códigos Añadidos | P1: Códigos Removidos
A2: Código | B2: Descripción | C2: Unidad | D2: Arancel | F2: Código | G2: Descripción | H2: Unidad | I2: Arancel | K2: 5209.19.91 | L2: Los demás tejidos. | M2: M² | N2: 35 | P2: 5401.10.01 | Q2: De filamentos sintéticos. | R2: Kg | S2: 30
A3: 3303.00.01 | B3: Aguas de tocador. | C3: L | D3: 25 | F3: 3303.00.01 | G3: Aguas de tocador. | H3: L | I3: 25 | K3: 5210.39.91 | L3: Los demás tejidos. | M3: M² | N3: 35 | P3: 5402.19.99 | Q3: Los demás. | R3: Kg | S3: 30
A4: 3303.00.99 | B4: Los demás. | C4: L | D4: 25 | F4: 3303.00.99 | G4: Los demás. | H4: L | I4: 25 | K4: 5211.49.91 | L4: Los demás tejidos. | M4: M² | N4: 35 | P4: 5402.20.02 | Q4: Hilados de alta tenacidad de poliésteres, incluso texturados | R4: Kg | S4: 30
A5: 3304.10.01 | B5: Preparaciones para el maquillaje de los labios. | C5: Kg | D5: 36 | F5: 3304.10.01 | G5: Preparaciones para el maquillaje de los labios. | H5: Kg | I5: 36 | K5: 5407.52.05 | L5: Teñidos. | M5: M² | N5: 35 | P5: 5402.33.01 | Q5: De poliésteres. | R5: Kg | S5: 30
A6: 3304.20.01 | B6: Preparaciones para el maquillaje de los ojos. | C6: Kg | D6: 25 | F6: 3304.20.01 | G6: Preparaciones para el maquillaje de los ojos. | H6: Kg | I6: 25 | K6: 5509.53.01 | L6: Mezclados exclusiva o principalmente con algodón. | M6: Kg | N6: 35 | P6: 5402.44.01 | Q6: De poliuretanos, del tipo de los denominados sin torsión, no en carretes de urdido (enjulios). | R6: Kg | S6: 30
A7: 3304.30.01 | B7: Preparaciones para manicuras o pedicuros. | C7: Kg | D7: 25 | F7: 3304.30.01 | G7: Preparaciones para manicuras o pedicuros. | H7: Kg | I7: 25 | K7: 5513.12.01 | L7: De fibras discontinuas de poliéster, de ligamento sarga, incluido el cruzado, de curso inferior o igual a 4. | M7: M² | N7: 25 | P7: 5402.46.91 | Q7: Los demás, de poliésteres, parcialmente orientados. | R7: Kg | S7: 30
A8: 3304.91.01 | B8: Polvos, incluidos los compactos. | C8: Kg | D8: 25 | F8: 3304.91.01 | G8: Polvos, incluidos los compactos. | H8: Kg | I8: 25 | K8: 6004.10.99 | L8: Los demás. | M8: Kg | N8: 35 | P8: 5404.11.01 | Q8: De poliuretanos, del tipo de los denominados "elastanos”. | R8: Kg | S8: 30
A9: 3304.99.01 | B9: Leches cutáneas. | C9: Kg | D9: 25 | F9: 3304.99.01 | G9: Leches cutáneas. | H9: Kg | I9: 25 | K9: 6006.32.03 | L9: Teñidos. | M9: Kg | N9: 35 | P9: 5503.20.03 | Q9: De tereftalato de polietileno color negro, teñidas en la masa | R9: Kg | S9: 30
A10: 3304.99.99 | B10: Las demás. | C10: Kg | D10: 25 | F10: 3304.99.99 | G10: Las demás. | H10: Kg | I10: 25 | K10: 6006.34.03 | L10: Estampados. | M10: Kg | N10: 35 | P10: 9513.12.01 | Q10: De fibras discontinuas de poliéster, de igamento sarga, incluido el cruzado, de curso inferior o igual a 4. | R10: M2 | S10: 25
A11: 3305.10.01 | B11: Champúes. | C11: Kg | D11: 25 | F11: 3305.10.01 | G11: Champúes. | H11: Kg | I11: 25
A12: 3305.20.01 | B12: Preparaciones para ondulación o desrizado permanentes. | C12: Kg | D12: 25 | F12: 3305.20.01 | G12: Preparaciones para ondulación o desrizado permanentes. | H12: Kg | I12: 25
A13: 3305.30.01 | B13: Lacas para el cabello. | C13: Kg | D13: 25 | F13: 3305.30.01 | G13: Lacas para el cabello. | H13: Kg | I13: 25
A14: 3305.90.99 | B14: Las demás. | C14: Kg | D14: 25 | F14: 3305.90.99 | G14: Las demás. | H14: Kg | I14: 25
A15: 3306.10.01 | B15: Dentífricos. | C15: Kg | D15: 30 | F15: 3306.10.01 | G15: Dentífricos. | H15: Kg | I15: 30
A16: 3306.20.02 | B16: Hilo utilizado para limpieza de los espacios interdentales (hilo dental). | C16: Kg | D16: 25 | F16: 3306.20.02 | G16: Hilo utilizado para limpieza de los espacios interdentales (hilo dental). | H16: Kg | I16: 25
A17: 3306.90.99 | B17: Los demás. | C17: Kg | D17: 25 | F17: 3306.90.99 | G17: Los demás. | H17: Kg | I17: 25
A18: 3307.10.01 | B18: Preparaciones para afeitar o para antes o después del afeitado. | C18: Kg | D18: 25 | F18: 3307.10.01 | G18: Preparaciones para afeitar o para antes o después del afeitado. | H18: Kg | I18: 25
A19: 3307.30.01 | B19: Sales perfumadas y demás preparaciones para el baño. | C19: Kg | D19: 25 | F19: 3307.30.01 | G19: Sales perfumadas y demás preparaciones para el baño. | H19: Kg | I19: 25
A20: 3307.41.01 | B20: "Agarbatti" y demás preparaciones odoríferas que actúan por combustión. | C20: Kg | D20: 25 | F20: 3307.41.01 | G20: "Agarbatti" y demás preparaciones odoríferas que actúan por combustión. | H20: Kg | I20: 25
A21: 3307.49.99 | B21: Las demás. | C21: Kg | D21: 25 | F21: 3307.49.99 | G21: Las demás. | H21: Kg | I21: 25
A22: 3307.90.99 | B22: Los demás. | C22: Kg | D22: 25 | F22: 3307.90.99 | G22: Los demás. | H22: Kg | I22: 25
... A1110: 7226.19.99 | B1110: Los demás. | C1110: Kg | D1110: 35 | F1110: 7228.30.99 | G1110: Las demás. | H1110: Kg | I1110: 35
A1111: 7226.20.01 | B1111: De acero rápido. | C1111: Kg | D1111: Ex. | F1111: 7228.40.91 | G1111: Las demás barras, simplemente forjadas. | H1111: Kg | I1111: 35
A1112: 7226.91.07 | B1112: Simplemente laminados en caliente. | C1112: Kg | D1112: 35 | F1112: 7228.50.91 | G1112: Las demás barras, simplemente obtenidas o acabadas en frío. | H1112: Kg | I1112: 35
A1113: 7226.92.06 | B1113: Simplemente laminados en frío. | C1113: Kg | D1113: 35 | F1113: 7228.60.91 | G1113: Las demás barras. | H1113: Kg | I1113: 35
A1114: 7226.99.99 | B1114: Los demás. | C1114: Kg | D1114: 35 | F1114: 7228.70.01 | G1114: Perfiles. | H1114: Kg | I1114: 35
A1115: 7227.10.01 | B1115: De acero rápido. | C1115: Kg | D1115: 35 | F1115: 7228.80.01 | G1115: Barras huecas para perforación. | H1115: Kg | I1115: 35
A1116: 7227.20.01 | B1116: De acero silicomanganeso. | C1116: Kg | D1116: 35 | F1116: 7229.20.01 | G1116: De acero silicomanganeso. | H1116: Kg | I1116: 35
A1117: 7227.90.99 | B1117: Los demás. | C1117: Kg | D1117: 35 | F1117: 7229.90.99 | G1117: Los demás. | H1117: Kg | I1117: 35
A1118: 7228.10.02 | B1118: Barras de acero rápido. | C1118: Kg | D1118: 35 | F1118: 7301.10.01 | G1118: Tablestacas. | H1118: Kg | I1118: 35
A1119: 7228.20.02 | B1119: Barras de acero silicomanganeso. | C1119: Kg | D1119: 35 | F1119: 7301.20.01 | G1119: Perfiles. | H1119: Kg | I1119: 35
A1120: 7228.30.99 | B1120: Las demás. | C1120: Kg | D1120: 35 | F1120: 7302.10.02 | G1120: Carriles (rieles). | H1120: Kg | I1120: 20
A1121: 7228.40.91 | B1121: Las demás barras, simplemente forjadas. | C1121: Kg | D1121: 35 | F1121: 7303.00.02 | G1121: Tubos y perfiles huecos, de fundición. | H1121: Kg | I1121: 35
A1122: 7228.50.91 | B1122: Las demás barras, simplemente obtenidas o acabadas en frío. | C1122: Kg | D1122: 35 | F1122: 7304.11.01 | G1122: Tubos laminados en caliente, sin recubrimiento u otros trabajos de superficie, incluidos los tubos laminados en caliente barnizados o laqueados: de diámetro exterior inferior o igual a 114.3 mm y espesor de pared superior o igual a 4 mm sin exceder de 19.5 mm. | H1122: Kg | I1122: 35
A1123: 7228.60.91 | B1123: Las demás barras. | C1123: Kg | D1123: 35 | F1123: 7304.11.02 | G1123: Tubos laminados en caliente, sin recubrimiento u otros trabajos de superficie, incluidos los tubos laminados en caliente barnizados o laqueados: de diámetro exterior superior a 114.3 mm sin exceder de 406.4 mm y espesor de pared superior o igual a 6.35 mm sin exceder de 38.1 mm. | H1123: Kg | I1123: 35
... A1130: 7302.10.02 | B1130: Carriles (rieles). | C1130: Kg | D1130: 20 | F1130: 7304.19.05 | G1130: Tubos semiterminados o esbozos para uso exclusivo de empresas fabricantes de tubería estirada en frío. | H1130: Kg | I1130: 35
A1131: 7302.40.02 | B1131: Bridas y placas de asiento. | C1131: Kg | D1131: Ex. | F1131: 7304.19.99 | G1131: Los demás. | H1131: Kg | I1131: 35
A1132: 7303.00.02 | B1132: Tubos y perfiles huecos, de fundición. | C1132: Kg | D1132: 35 | F1132: 7304.24.91 | G1132: Los demás, de acero inoxidable. | H1132: Kg | I1132: 35
A1133: 7304.11.01 | B1133: Tubos laminados en caliente, sin recubrimiento u otros trabajos de superficie, incluidos los tubos laminados en caliente barnizados o laqueados: de diámetro exterior inferior o igual a 114.3 mm y espesor de pared superior o igual a 4 mm sin exceder de 19.5 mm. | C1133: Kg | D1133: 35 | F1133: 7304.29.99 | G1133: Los demás. | H1133: Kg | I1133: 35
A1134: 7304.11.02 | B1134: Tubos laminados en caliente, sin recubrimiento u otros trabajos de superficie, incluidos los tubos laminados en caliente barnizados o laqueados: de diámetro exterior superior a 114.3 mm sin exceder de 406.4 mm y espesor de pared superior o igual a 6.35 mm sin exceder de 38.1 mm. | C1134: Kg | D1134: 35 | F1134: 7304.31.01 | G1134: Tubos llamados "mecánicos" o "estructurales", sin recubrimientos u otros trabajos de superficie, de diámetro exterior inferior o igual a 114.3 mm y espesor de pared superior o igual a 1.27 mm sin exceder de 9.5 mm. | H1134: Kg | I1134: 25
A1135: 7304.11.03 | B1135: Tubos laminados en caliente, sin recubrimiento u otros trabajos de superficie, incluidos los tubos laminados en caliente barnizados o laqueados: de diámetro exterior superior a 406.4 mm y espesor de pared superior o igual a 9.52 mm sin exceder de 31.75 mm. | C1135: Kg | D1135: 35 | F1135: 7304.31.10 | G1135: Tubos llamados "térmicos" o de "conducción", sin recubrimientos u otros trabajos de superficie, de diámetro exterior inferior o igual a 114.3 mm y espesor de pared superior o igual a 1.27 mm sin exceder de 9.5 mm. | H1135: Kg | I1135: 25
A1136: 7304.11.04 | B1136: Tubos laminados en frío, sin recubrimiento u otros trabajos de superficie, incluidos los tubos laminados en frío barnizados o laqueados: de diámetro exterior inferior o igual a 114.3 mm y espesor de pared superior o igual a 1.27 mm sin exceder de 9.5 mm.} | C1136: Kg | D1136: 35 | F1136: 7304.31.99 | G1136: Los demás. | H1136: Kg | I1136: 25
A1137: 7304.11.99 | B1137: Los demás. | C1137: Kg | D1137: 35 | F1137: 7304.39.01 | G1137: Tubos llamados "mecánicos" o "estructurales", laminados en caliente, sin recubrimiento o trabajos de superficie, incluidos los tubos llamados "mecánicos" o "estructurales" laminados en caliente, laqueados o barnizados: de diámetro exterior inferior o igual a 114.3 mm, y espesor de pared superior o igual a 4 mm sin exceder de 19.5 mm. | H1137: Kg | I1137: 35
A1138: 7304.19.01 | B1138: Tubos laminados en caliente, sin recubrimiento u otros trabajos de superficie, incluidos los tubos laminados en caliente barnizados o laqueados: de diámetro exterior inferior o igual a 114.3 mm y espesor de pared superior o igual a 4 mm sin exceder de 19.5 mm. | C1138: Kg | D1138: 35 | F1138: 7304.39.03 | G1138: Barras huecas laminadas en caliente, con diámetro exterior superior a 30 mm sin exceder de 50 mm, así como las de diámetro exterior superior a 300 mm. | H1138: Kg | I1138: 35
A1139: 7304.19.02 | B1139: Tubos laminados en caliente, sin recubrimiento u otros trabajos de superficie, incluidos los tubos laminados en caliente barnizados o laqueados: de diámetro exterior superior a 114.3 mm sin exceder de 406.4 mm y espesor de pared superior o igual a 6.35 mm sin exceder de 38.1 mm. | C1139: Kg | D1139: 35 | F1139: 7304.39.08 | G1139: Tubos aletados o con birlos. | H1139: Kg | I1139: 35
A1140: 7304.19.04 | B1140: Tubos laminados en frío, sin recubrimiento u otros trabajos de superficie, incluidos los tubos laminados en frío barnizados o laqueados: de diámetro exterior inferior o igual a 114.3 mm y espesor de pared superior o igual a 1.27 mm sin exceder de 9.5 mm. | C1140: Kg | D1140: 35 | F1140: 7304.39.09 | G1140: Tubos semiterminados o esbozos, sin recubrimiento u otros trabajos de superficie, de diámetro exterior superior o igual a 20 mm sin exceder de 460 mm y espesor de pared superior o igual a 2.8 mm sin exceder de 35.4 mm, con extremos lisos, biselados, recalcados y/o con rosca y cople. | H1140: Kg | I1140: 35
A1141: 7304.19.05 | B1141: Tubos semiterminados o esbozos para uso exclusivo de empresas fabricantes de tubería estirada en frío. | C1141: Kg | D1141: 35 | F1141: 7304.39.10 | G1141: Tubos llamados "térmicos", sin recubrimientos distintos de los obtenidos por laqueado y barnizado o sin trabajos de superficie, de diámetro exterior inferior o igual a 114.3 mm y espesor de pared superior o igual a 4 mm, sin exceder 19.5 mm. | H1141: Kg | I1141: 35
A1142: 7304.19.99 | B1142: Los demás. | C1142: Kg | D1142: 35 | F1142: 7304.39.11 | G1142: Tubos llamados de "conducción", sin recubrimientos distintos de los obtenidos por laqueado y barnizado o sin trabajos de superficie, de diámetro exterior inferior o igual a 114.3 mm y espesor de pared superior o igual a 4 mm, sin exceder 19.5 mm. | H1142: Kg | I1142: 35
A1143: 7304.24.91 | B1143: Los demás, de acero inoxidable. | C1143: Kg | D1143: 35 | F1143: 7304.39.12 | G1143: Tubos llamados "térmicos", sin recubrimientos distintos de los obtenidos por laqueado y barnizado o sin trabajos de superficie, de diámetro exterior superior a 114.3 mm sin exceder de 406.4 mm y espesor de pared superior o igual a 6.35 mm sin exceder de 38.1 mm. | H1143: Kg | I1143: 35
... A1454: 9503.00.28 | B1454: Prendas, complementos (accesorios) de vestir, calzado, sombreros y demás tocados, para muñecas y muñecos que representen solamente seres humanos. | C1454: Kg | D1454: 30 | F1454: 9619.00.03 | G1454: Pañales y artículos similares, de otras materias textiles, excepto lo comprendido en la fracción arancelaria 9619.00.02. | H1454: Pza | I1454: 35
A1455: 9503.00.35 | B1455: Partes, piezas y accesorios, reconocibles como diseñadas para coches y sillas de ruedas para muñecas o muñecos, para los demás juguetes de rueda, o para lo comprendido en las fracciones arancelarias 9503.00.21, 9503.00.25 o 9503.00.26. | C1455: Kg | D1455: 30
A1456: 9503.00.91 | B1456: Los demás juguetes con ruedas diseñados para que los conduzcan los niños; coches y sillas de ruedas para muñecas o muñecos. | C1456: Pza | D1456: 30
A1457: 9503.00.92 | B1457: Las demás muñecas y muñecos que representen solamente seres humanos, incluso vestidos, excepto lo comprendido en las fracciones arancelarias 9503.00.04. y 9503.00.05. | C1457: Pza | D1457: 30
A1458: 9503.00.93 | B1458: Los demás juguetes que representen animales o seres no humanos, sin rellenar. | C1458: Kg | D1458: 30
A1459: 9503.00.99 | B1459: Los demás. | C1459: Kg | D1459: 30
A1460: 9504.40.01 | B1460: Naipes. | C1460: Kg | D1460: 30
A1461: 9505.90.99 | B1461: Los demás. | C1461: Kg | D1461: 30
A1462: 9613.90.01 | B1462: Reconocibles como diseñadas exclusivamente para los encendedores de cigarrillos a base de resistencia para uso automotriz. | C1462: Kg | D1462: 25
A1463: 9619.00.01 | B1463: De pasta de papel, papel, guata de celulosa o napa de fibras de celulosa. | C1463: Kg | D1463: 35
A1464: 9619.00.02 | B1464: De guata de materia textil. | C1464: Kg | D1464: 35
A1465: 9619.00.03 | B1465: Pañales y artículos similares, de otras materias textiles, excepto lo comprendido en la fracción arancelaria 9619.00.02. | C1465: Pza | D1465: 35

Sheet Jul vs Dic
A1: Código | B1: Descripción HS6 | C1: Descripción HS8 | D1: Unidad | E1: Arancel Julio | F1: Arancel Diciembre | G1: Relación
A2: 0101.21.01 | B2: Animales vivos y productos del reino animal. Animales vivos. Caballos, asnos, mulos y burdéganos, vivos. Caballos: Reproductores de raza pura. | C2: Reproductores de raza pura. | D2: Cbza | E2: 10 | F2: =_xlfn.IFNA(VLOOKUP(A2,'LIGIE Diciembre DOF'!$A$3:$D$1465,4,FALSE),"---") -> --- | G2: {=_xlfn.IFS(F2="---","Sin Cambios",E2=F2,"Sin Cambios",E2<>F2,"Modificado")} -> Sin Cambios
A3: 0101.29.02 | B3: Animales vivos y productos del reino animal. Animales vivos. Caballos, asnos, mulos y burdéganos, vivos. Caballos: Los demás. | C3: Sin pedigree, para reproducción. | D3: Pza | E3: 10 | F3: =_xlfn.IFNA(VLOOKUP(A3,'LIGIE Diciembre DOF'!$A$3:$D$1465,4,FALSE),"---") -> --- | G3: {=_xlfn.IFS(F3="---","Sin Cambios",E3=F3,"Sin Cambios",E3<>F3,"Modificado")} -> Sin Cambios
A4: 0101.29.03 | B4: Animales vivos y productos del reino animal. Animales vivos. Caballos, asnos, mulos y burdéganos, vivos. Caballos: Los demás. | C4: Para abasto, cuando la importación la realicen empacadoras Tipo Inspección Federal. | D4: Pza | E4: 10 | F4: =_xlfn.IFNA(VLOOKUP(A4,'LIGIE Diciembre DOF'!$A$3:$D$1465,4,FALSE),"---") -> --- | G4: {=_xlfn.IFS(F4="---","Sin Cambios",E4=F4,"Sin Cambios",E4<>F4,"Modificado")} -> Sin Cambios
A5: 0101.29.99 | B5: Animales vivos y productos del reino animal. Animales vivos. Caballos, asnos, mulos y burdéganos, vivos. Caballos: Los demás. | C5: Los demás. | D5: Pza | E5: 20 | F5: =_xlfn.IFNA(VLOOKUP(A5,'LIGIE Diciembre DOF'!$A$3:$D$1465,4,FALSE),"---") -> --- | G5: {=_xlfn.IFS(F5="---","Sin Cambios",E5=F5,"Sin Cambios",E5<>F5,"Modificado")} -> Sin Cambios
A6: 0101.30.01 | B6: Animales vivos y productos del reino animal. Animales vivos. Caballos, asnos, mulos y burdéganos, vivos. Asnos. | C6: Asnos. | D6: Cbza | E6: 20 | F6: =_xlfn.IFNA(VLOOKUP(A6,'LIGIE Diciembre DOF'!$A$3:$D$1465,4,FALSE),"---") -> --- | G6: {=_xlfn.IFS(F6="---","Sin Cambios",E6=F6,"Sin Cambios",E6<>F6,"Modificado")} -> Sin Cambios
A7: 0101.90.99 | B7: Animales vivos y productos del reino animal. Animales vivos. Caballos, asnos, mulos y burdéganos, vivos. Los demás. | C7: Los demás. | D7: Cbza | E7: 20 | F7: =_xlfn.IFNA(VLOOKUP(A7,'LIGIE Diciembre DOF'!$A$3:$D$1465,4,FALSE),"---") -> --- | G7: {=_xlfn.IFS(F7="---","Sin Cambios",E7=F7,"Sin Cambios",E7<>F7,"Modificado")} -> Sin Cambios
A8: 0102.21.01 | B8: Animales vivos y productos del reino animal. Animales vivos. Animales vivos de la especie bovina. Bovinos domésticos: Reproductores de raza pura. | C8: Reproductores de raza pura. | D8: Cbza | E8: Ex. | F8: =_xlfn.IFNA(VLOOKUP(A8,'LIGIE Diciembre DOF'!$A$3:$D$1465,4,FALSE),"---") -> --- | G8: {=_xlfn.IFS(F8="---","Sin Cambios",E8=F8,"Sin Cambios",E8<>F8,"Modificado")} -> Sin Cambios
A9: 0102.29.01 | B9: Animales vivos y productos del reino animal. Animales vivos. Animales vivos de la especie bovina. Bovinos domésticos: Los demás. | C9: Vacas lecheras. | D9: Pza | E9: Ex. | F9: =_xlfn.IFNA(VLOOKUP(A9,'LIGIE Diciembre DOF'!$A$3:$D$1465,4,FALSE),"---") -> --- | G9: {=_xlfn.IFS(F9="---","Sin Cambios",E9=F9,"Sin Cambios",E9<>F9,"Modificado")} -> Sin Cambios
A10: 0102.29.02 | B10: Animales vivos y productos del reino animal. Animales vivos. Animales vivos de la especie bovina. Bovinos domésticos: Los demás. | C10: Con pedigree o certificado de alto registro, excepto lo comprendido en la fracción arancelaria 0102.29.01. | D10: Pza | E10: Ex. | F10: =_xlfn.IFNA(VLOOKUP(A10,'LIGIE Diciembre DOF'!$A$3:$D$1465,4,FALSE),"---") -> --- | G10: {=_xlfn.IFS(F10="---","Sin Cambios",E10=F10,"Sin Cambios",E10<>F10,"Modificado")} -> Sin Cambios
A11: 0102.29.99 | B11: Animales vivos y productos del reino animal. Animales vivos. Animales vivos de la especie bovina. Bovinos domésticos: Los demás. | C11: Los demás. | D11: Pza | E11: 15 | F11: =_xlfn.IFNA(VLOOKUP(A11,'LIGIE Diciembre DOF'!$A$3:$D$1465,4,FALSE),"---") -> --- | G11: {=_xlfn.IFS(F11="---","Sin Cambios",E11=F11,"Sin Cambios",E11<>F11,"Modificado")} -> Sin Cambios
A12: 0102.31.01 | B12: Animales vivos y productos del reino animal. Animales vivos. Animales vivos de la especie bovina. Búfalos: Reproductores de raza pura. | C12: Reproductores de raza pura. | D12: Cbza | E12: Ex. | F12: =_xlfn.IFNA(VLOOKUP(A12,'LIGIE Diciembre DOF'!$A$3:$D$1465,4,FALSE),"---") -> --- | G12: {=_xlfn.IFS(F12="---","Sin Cambios",E12=F12,"Sin Cambios",E12<>F12,"Modificado")} -> Sin Cambios
A13: 0102.39.99 | B13: Animales vivos y productos del reino animal. Animales vivos. Animales vivos de la especie bovina. Búfalos: Los demás. | C13: Los demás. | D13: Cbza | E13: 15 | F13: =_xlfn.IFNA(VLOOKUP(A13,'LIGIE Diciembre DOF'!$A$3:$D$1465,4,FALSE),"---") -> --- | G13: {=_xlfn.IFS(F13="---","Sin Cambios",E13=F13,"Sin Cambios",E13<>F13,"Modificado")} -> Sin Cambios
A14: 0102.90.99 | B14: Animales vivos y productos del reino animal. Animales vivos. Animales vivos de la especie bovina. Los demás. | C14: Los demás. | D14: Cbza | E14: 15 | F14: =_xlfn.IFNA(VLOOKUP(A14,'LIGIE Diciembre DOF'!$A$3:$D$1465,4,FALSE),"---") -> --- | G14: {=_xlfn.IFS(F14="---","Sin Cambios",E14=F14,"Sin Cambios",E14<>F14,"Modificado")} -> Sin Cambios
A15: 0103.10.01 | B15: Animales vivos y productos del reino animal. Animales vivos. Animales vivos de la especie porcina. Reproductores de raza pura. | C15: Reproductores de raza pura. | D15: Cbza | E15: Ex. | F15: =_xlfn.IFNA(VLOOKUP(A15,'LIGIE Diciembre DOF'!$A$3:$D$1465,4,FALSE),"---") -> --- | G15: {=_xlfn.IFS(F15="---","Sin Cambios",E15=F15,"Sin Cambios",E15<>F15,"Modificado")} -> Sin Cambios
A16: 0103.91.01 | B16: Animales vivos y productos del reino animal. Animales vivos. Animales vivos de la especie porcina. Los demás: De peso inferior a 50 kg. | C16: Con pedigree o certificado de alto registro. | D16: Cbza | E16: 9 | F16: =_xlfn.IFNA(VLOOKUP(A16,'LIGIE Diciembre DOF'!$A$3:$D$1465,4,FALSE),"---") -> --- | G16: {=_xlfn.IFS(F16="---","Sin Cambios",E16=F16,"Sin Cambios",E16<>F16,"Modificado")} -> Sin Cambios
A17: 0103.91.99 | B17: Animales vivos y productos del reino animal. Animales vivos. Animales vivos de la especie porcina. Los demás: De peso inferior a 50 kg. | C17: Los demás. | D17: Cbza | E17: 20 | F17: =_xlfn.IFNA(VLOOKUP(A17,'LIGIE Diciembre DOF'!$A$3:$D$1465,4,FALSE),"---") -> --- | G17: {=_xlfn.IFS(F17="---","Sin Cambios",E17=F17,"Sin Cambios",E17<>F17,"Modificado")} -> Sin Cambios
A18: 0103.92.01 | B18: Animales vivos y productos del reino animal. Animales vivos. Animales vivos de la especie porcina. Los demás: De peso superior o igual a 50 kg. | C18: Con pedigree o certificado de alto registro. | D18: Cbza | E18: 9 | F18: =_xlfn.IFNA(VLOOKUP(A18,'LIGIE Diciembre DOF'!$A$3:$D$1465,4,FALSE),"---") -> --- | G18: {=_xlfn.IFS(F18="---","Sin Cambios",E18=F18,"Sin Cambios",E18<>F18,"Modificado")} -> Sin Cambios
A19: 0103.92.99 | B19: Animales vivos y productos del reino animal. Animales vivos. Animales vivos de la especie porcina. Los demás: De peso superior o igual a 50 kg. | C19: Los demás. | D19: Cbza | E19: 20 | F19: =_xlfn.IFNA(VLOOKUP(A19,'LIGIE Diciembre DOF'!$A$3:$D$1465,4,FALSE),"---") -> --- | G19: {=_xlfn.IFS(F19="---","Sin Cambios",E19=F19,"Sin Cambios",E19<>F19,"Modificado")} -> Sin Cambios
A20: 0104.10.01 | B20: Animales vivos y productos del reino animal. Animales vivos. Animales vivos de las especies ovina o caprina. De la especie ovina. | C20: Con pedigree o certificado de alto registro. | D20: Pza | E20: Ex. | F20: =_xlfn.IFNA(VLOOKUP(A20,'LIGIE Diciembre DOF'!$A$3:$D$1465,4,FALSE),"---") -> --- | G20: {=_xlfn.IFS(F20="---","Sin Cambios",E20=F20,"Sin Cambios",E20<>F20,"Modificado")} -> Sin Cambios
A21: 0104.10.99 | B21: Animales vivos y productos del reino animal. Animales vivos. Animales vivos de las especies ovina o caprina. De la especie ovina. | C21: Los demás. | D21: Pza | E21: 10 | F21: =_xlfn.IFNA(VLOOKUP(A21,'LIGIE Diciembre DOF'!$A$3:$D$1465,4,FALSE),"---") -> --- | G21: {=_xlfn.IFS(F21="---","Sin Cambios",E21=F21,"Sin Cambios",E21<>F21,"Modificado")} -> Sin Cambios
A22: 0104.20.01 | B22: Animales vivos y productos del reino animal. Animales vivos. Animales vivos de las especies ovina o caprina. De la especie caprina. | C22: Con pedigree o certificado de alto registro. | D22: Cbza | E22: Ex. | F22: =_xlfn.IFNA(VLOOKUP(A22,'LIGIE Diciembre DOF'!$A$3:$D$1465,4,FALSE),"---") -> --- | G22: {=_xlfn.IFS(F22="---","Sin Cambios",E22=F22,"Sin Cambios",E22<>F22,"Modificado")} -> Sin Cambios
A23: 0104.20.02 | B23: Animales vivos y productos del reino animal. Animales vivos. Animales vivos de las especies ovina o caprina. De la especie caprina. | C23: Borrego cimarrón. | D23: Cbza | E23: 20 | F23: =_xlfn.IFNA(VLOOKUP(A23,'LIGIE Diciembre DOF'!$A$3:$D$1465,4,FALSE),"---") -> --- | G23: {=_xlfn.IFS(F23="---","Sin Cambios",E23=F23,"Sin Cambios",E23<>F23,"Modificado")} -> Sin Cambios
A24: 0104.20.99 | B24: Animales vivos y productos del reino animal. Animales vivos. Animales vivos de las especies ovina o caprina. De la especie caprina. | C24: Los demás. | D24: Cbza | E24: 10 | F24: =_xlfn.IFNA(VLOOKUP(A24,'LIGIE Diciembre DOF'!$A$3:$D$1465,4,FALSE),"---") -> --- | G24: {=_xlfn.IFS(F24="---","Sin Cambios",E24=F24,"Sin Cambios",E24<>F24,"Modificado")} -> Sin Cambios
A25: 0105.11.03 | B25: Animales vivos y productos del reino animal. Animales vivos. Gallos, gallinas, patos, gansos, pavos (gallipavos) y pintadas, de las especies domésticas, vivos. De peso inferior o igual a 185 g: Aves de la especie Gallus domesticus. | C25: Recién nacidos, de tres días o menos. | D25: Pza | E25: Ex. | F25: =_xlfn.IFNA(VLOOKUP(A25,'LIGIE Diciembre DOF'!$A$3:$D$1465,4,FALSE),"---") -> --- | G25: {=_xlfn.IFS(F25="---","Sin Cambios",E25=F25,"Sin Cambios",E25<>F25,"Modificado")} -> Sin Cambios
A26: 0105.11.99 | B26: Animales vivos y productos del reino animal. Animales vivos. Gallos, gallinas, patos, gansos, pavos (gallipavos) y pintadas, de las especies domésticas, vivos. De peso inferior o igual a 185 g: Aves de la especie Gallus domesticus. | C26: Los demás. | D26: Pza | E26: 10 | F26: =_xlfn.IFNA(VLOOKUP(A26,'LIGIE Diciembre DOF'!$A$3:$D$1465,4,FALSE),"---") -> --- | G26: {=_xlfn.IFS(F26="---","Sin Cambios",E26=F26,"Sin Cambios",E26<>F26,"Modificado")} -> Sin Cambios
A27: 0105.12.01 | B27: Animales vivos y productos del reino animal. Animales vivos. Gallos, gallinas, patos, gansos, pavos (gallipavos) y pintadas, de las especies domésticas, vivos. De peso inferior o igual a 185 g: Pavos (gallipavos). | C27: Pavos (gallipavos). | D27: Pza | E27: 10 | F27: =_xlfn.IFNA(VLOOKUP(A27,'LIGIE Diciembre DOF'!$A$3:$D$1465,4,FALSE),"---") -> --- | G27: {=_xlfn.IFS(F27="---","Sin Cambios",E27=F27,"Sin Cambios",E27<>F27,"Modificado")} -> Sin Cambios
A28: 0105.13.01 | B28: Animales vivos y productos del reino animal. Animales vivos. Gallos, gallinas, patos, gansos, pavos (gallipavos) y pintadas, de las especies domésticas, vivos. De peso inferior o igual a 185 g: Patos. | C28: Patos. | D28: Cbza | E28: 10 | F28: =_xlfn.IFNA(VLOOKUP(A28,'LIGIE Diciembre DOF'!$A$3:$D$1465,4,FALSE),"---") -> --- | G28: {=_xlfn.IFS(F28="---","Sin Cambios",E28=F28,"Sin Cambios",E28<>F28,"Modificado")} -> Sin Cambios
A29: 0105.14.01 | B29: Animales vivos y productos del reino animal. Animales vivos. Gallos, gallinas, patos, gansos, pavos (gallipavos) y pintadas, de las especies domésticas, vivos. De peso inferior o igual a 185 g: Gansos. | C29: Gansos. | D29: Cbza | E29: 10 | F29: =_xlfn.IFNA(VLOOKUP(A29,'LIGIE Diciembre DOF'!$A$3:$D$1465,4,FALSE),"---") -> --- | G29: {=_xlfn.IFS(F29="---","Sin Cambios",E29=F29,"Sin Cambios",E29<>F29,"Modificado")} -> Sin Cambios
A30: 0105.15.01 | B30: Animales vivos y productos del reino animal. Animales vivos. Gallos, gallinas, patos, gansos, pavos (gallipavos) y pintadas, de las especies domésticas, vivos. De peso inferior o igual a 185 g: Pintadas. | C30: Pintadas. | D30: Cbza | E30: 10 | F30: =_xlfn.IFNA(VLOOKUP(A30,'LIGIE Diciembre DOF'!$A$3:$D$1465,4,FALSE),"---") -> --- | G30: {=_xlfn.IFS(F30="---","Sin Cambios",E30=F30,"Sin Cambios",E30<>F30,"Modificado")} -> Sin Cambios
A31: 0105.94.01 | B31: Animales vivos y productos del reino animal. Animales vivos. Gallos, gallinas, patos, gansos, pavos (gallipavos) y pintadas, de las especies domésticas, vivos. Los demás: Aves de la especie Gallus domesticus. | C31: Gallos de pelea. | D31: Cbza | E31: 20 | F31: =_xlfn.IFNA(VLOOKUP(A31,'LIGIE Diciembre DOF'!$A$3:$D$1465,4,FALSE),"---") -> --- | G31: {=_xlfn.IFS(F31="---","Sin Cambios",E31=F31,"Sin Cambios",E31<>F31,"Modificado")} -> Sin Cambios
A32: 0105.94.99 | B32: Animales vivos y productos del reino animal. Animales vivos. Gallos, gallinas, patos, gansos, pavos (gallipavos) y pintadas, de las especies domésticas, vivos. Los demás: Aves de la especie Gallus domesticus. | C32: Los demás. | D32: Cbza | E32: 10 | F32: =_xlfn.IFNA(VLOOKUP(A32,'LIGIE Diciembre DOF'!$A$3:$D$1465,4,FALSE),"---") -> --- | G32: {=_xlfn.IFS(F32="---","Sin Cambios",E32=F32,"Sin Cambios",E32<>F32,"Modificado")} -> Sin Cambios
A33: 0105.99.99 | B33: Animales vivos y productos del reino animal. Animales vivos. Gallos, gallinas, patos, gansos, pavos (gallipavos) y pintadas, de las especies domésticas, vivos. Los demás: Los demás. | C33: Los demás. | D33: Cbza | E33: 10 | F33: =_xlfn.IFNA(VLOOKUP(A33,'LIGIE Diciembre DOF'!$A$3:$D$1465,4,FALSE),"---") -> --- | G33: {=_xlfn.IFS(F33="---","Sin Cambios",E33=F33,"Sin Cambios",E33<>F33,"Modificado")} -> Sin Cambios
A34: 0106.11.01 | B34: Animales vivos y productos del reino animal. Animales vivos. Los demás animales vivos. Mamíferos: Primates. | C34: Monos (simios) de las variedades Macacus rhesus o Macacus cercophitecus. | D34: Cbza | E34: 10 | F34: =_xlfn.IFNA(VLOOKUP(A34,'LIGIE Diciembre DOF'!$A$3:$D$1465,4,FALSE),"---") -> --- | G34: {=_xlfn.IFS(F34="---","Sin Cambios",E34=F34,"Sin Cambios",E34<>F34,"Modificado")} -> Sin Cambios
A35: 0106.11.99 | B35: Animales vivos y productos del reino animal. Animales vivos. Los demás animales vivos. Mamíferos: Primates. | C35: Los demás. | D35: Cbza | E35: 20 | F35: =_xlfn.IFNA(VLOOKUP(A35,'LIGIE Diciembre DOF'!$A$3:$D$1465,4,FALSE),"---") -> --- | G35: {=_xlfn.IFS(F35="---","Sin Cambios",E35=F35,"Sin Cambios",E35<>F35,"Modificado")} -> Sin Cambios
A36: 0106.12.01 | B36: Animales vivos y productos del reino animal. Animales vivos. Los demás animales vivos. Mamíferos: Ballenas, delfines y marsopas (mamíferos del orden Cetacea); manatíes y dugones o dugongos (mamíferos del orden Sirenia); otarios y focas, leones marinos y morsas (mamíferos del suborden Pinnipedia). | C36: Ballenas, delfines y marsopas (mamíferos del orden Cetacea); manatíes y dugones o dugongos (mamíferos del orden Sirenia); otarios y focas, leones marinos y morsas (mamíferos del suborden Pinnipedia). | D36: Cbza | E36: 20 | F36: =_xlfn.IFNA(VLOOKUP(A36,'LIGIE Diciembre DOF'!$A$3:$D$1465,4,FALSE),"---") -> --- | G36: {=_xlfn.IFS(F36="---","Sin Cambios",E36=F36,"Sin Cambios",E36<>F36,"Modificado")} -> Sin Cambios
A37: 0106.13.01 | B37: Animales vivos y productos del reino animal. Animales vivos. Los demás animales vivos. Mamíferos: Camellos y demás camélidos (Camelidae). | C37: Camellos y demás camélidos (Camelidae). | D37: Cbza | E37: 20 | F37: =_xlfn.IFNA(VLOOKUP(A37,'LIGIE Diciembre DOF'!$A$3:$D$1465,4,FALSE),"---") -> --- | G37: {=_xlfn.IFS(F37="---","Sin Cambios",E37=F37,"Sin Cambios",E37<>F37,"Modificado")} -> Sin Cambios
A38: 0106.14.01 | B38: Animales vivos y productos del reino animal. Animales vivos. Los demás animales vivos. Mamíferos: Conejos y liebres. | C38: Conejos y liebres. | D38: Cbza | E38: 20 | F38: =_xlfn.IFNA(VLOOKUP(A38,'LIGIE Diciembre DOF'!$A$3:$D$1465,4,FALSE),"---") -> --- | G38: {=_xlfn.IFS(F38="---","Sin Cambios",E38=F38,"Sin Cambios",E38<>F38,"Modificado")} -> Sin Cambios
A39: 0106.19.02 | B39: Animales vivos y productos del reino animal. Animales vivos. Los demás animales vivos. Mamíferos: Los demás. | C39: Venado rojo (Cervus elaphus); gamo (Dama dama). | D39: Cbza | E39: Ex. | F39: =_xlfn.IFNA(VLOOKUP(A39,'LIGIE Diciembre DOF'!$A$3:$D$1465,4,FALSE),"---") -> --- | G39: {=_xlfn.IFS(F39="---","Sin Cambios",E39=F39,"Sin Cambios",E39<>F39,"Modificado")} -> Sin Cambios
A40: 0106.19.99 | B40: Animales vivos y productos del reino animal. Animales vivos. Los demás animales vivos. Mamíferos: Los demás. | C40: Los demás. | D40: Cbza | E40: 20 | F40: =_xlfn.IFNA(VLOOKUP(A40,'LIGIE Diciembre DOF'!$A$3:$D$1465,4,FALSE),"---") -> --- | G40: {=_xlfn.IFS(F40="---","Sin Cambios",E40=F40,"Sin Cambios",E40<>F40,"Modificado")} -> Sin Cambios
A41: 0106.20.04 | B41: Animales vivos y productos del reino animal. Animales vivos. Los demás animales vivos. Reptiles (incluidas las serpientes y tortugas de mar). | C41: Reptiles (incluidas las serpientes y tortugas de mar). | D41: Cbza | E41: 20 | F41: =_xlfn.IFNA(VLOOKUP(A41,'LIGIE Diciembre DOF'!$A$3:$D$1465,4,FALSE),"---") -> --- | G41: {=_xlfn.IFS(F41="---","Sin Cambios",E41=F41,"Sin Cambios",E41<>F41,"Modificado")} -> Sin Cambios
A42: 0106.31.01 | B42: Animales vivos y productos del reino animal. Animales vivos. Los demás animales vivos. Aves: Aves de rapiña. | C42: Aves de rapiña. | D42: Pza | E42: 20 | F42: =_xlfn.IFNA(VLOOKUP(A42,'LIGIE Diciembre DOF'!$A$3:$D$1465,4,FALSE),"---") -> --- | G42: {=_xlfn.IFS(F42="---","Sin Cambios",E42=F42,"Sin Cambios",E42<>F42,"Modificado")} -> Sin Cambios
A43: 0106.32.01 | B43: Animales vivos y productos del reino animal. Animales vivos. Los demás animales vivos. Aves: Psitaciformes (incluidos los loros, guacamayos, cacatúas y demás papagayos). | C43: Psitaciformes (incluidos los loros, guacamayos, cacatúas y demás papagayos). | D43: Cbza | E43: 20 | F43: =_xlfn.IFNA(VLOOKUP(A43,'LIGIE Diciembre DOF'!$A$3:$D$1465,4,FALSE),"---") -> --- | G43: {=_xlfn.IFS(F43="---","Sin Cambios",E43=F43,"Sin Cambios",E43<>F43,"Modificado")} -> Sin Cambios
A44: 0106.33.01 | B44: Animales vivos y productos del reino animal. Animales vivos. Los demás animales vivos. Aves: Avestruces; emúes (Dromaius novaehollandiae). | C44: Avestruces; emúes (Dromaius novaehollandiae). | D44: Cbza | E44: 20 | F44: =_xlfn.IFNA(VLOOKUP(A44,'LIGIE Diciembre DOF'!$A$3:$D$1465,4,FALSE),"---") -> --- | G44: {=_xlfn.IFS(F44="---","Sin Cambios",E44=F44,"Sin Cambios",E44<>F44,"Modificado")} -> Sin Cambios
A45: 0106.39.99 | B45: Animales vivos y productos del reino animal. Animales vivos. Los demás animales vivos. Aves: Las demás. | C45: Las demás. | D45: Cbza | E45: 20 | F45: =_xlfn.IFNA(VLOOKUP(A45,'LIGIE Diciembre DOF'!$A$3:$D$1465,4,FALSE),"---") -> --- | G45: {=_xlfn.IFS(F45="---","Sin Cambios",E45=F45,"Sin Cambios",E45<>F45,"Modificado")} -> Sin Cambios
A46: 0106.41.01 | B46: Animales vivos y productos del reino animal. Animales vivos. Los demás animales vivos. Insectos: Abejas. | C46: Abejas. | D46: Kg | E46: 10 | F46: =_xlfn.IFNA(VLOOKUP(A46,'LIGIE Diciembre DOF'!$A$3:$D$1465,4,FALSE),"---") -> --- | G46: {=_xlfn.IFS(F46="---","Sin Cambios",E46=F46,"Sin Cambios",E46<>F46,"Modificado")} -> Sin Cambios
A47: 0106.49.99 | B47: Animales vivos y productos del reino animal. Animales vivos. Los demás animales vivos. Insectos: Los demás. | C47: Los demás. | D47: Kg | E47: 20 | F47: =_xlfn.IFNA(VLOOKUP(A47,'LIGIE Diciembre DOF'!$A$3:$D$1465,4,FALSE),"---") -> --- | G47: {=_xlfn.IFS(F47="---","Sin Cambios",E47=F47,"Sin Cambios",E47<>F47,"Modificado")} -> Sin Cambios
A48: 0106.90.02 | B48: Animales vivos y productos del reino animal. Animales vivos. Los demás animales vivos. Los demás. | C48: Lombriz Rebellus (Lumbricus rubellus). | D48: Kg | E48: 10 | F48: =_xlfn.IFNA(VLOOKUP(A48,'LIGIE Diciembre DOF'!$A$3:$D$1465,4,FALSE),"---") -> --- | G48: {=_xlfn.IFS(F48="---","Sin Cambios",E48=F48,"Sin Cambios",E48<>F48,"Modificado")} -> Sin Cambios
A49: 0106.90.03 | B49: Animales vivos y productos del reino animal. Animales vivos. Los demás animales vivos. Los demás. | C49: Lombriz acuática. | D49: Kg | E49: Ex. | F49: =_xlfn.IFNA(VLOOKUP(A49,'LIGIE Diciembre DOF'!$A$3:$D$1465,4,FALSE),"---") -> --- | G49: {=_xlfn.IFS(F49="---","Sin Cambios",E49=F49,"Sin Cambios",E49<>F49,"Modificado")} -> Sin Cambios
A50: 0106.90.04 | B50: Animales vivos y productos del reino animal. Animales vivos. Los demás animales vivos. Los demás. | C50: Ácaros Phytoseiulus persimilis. | D50: Kg | E50: Ex. | F50: =_xlfn.IFNA(VLOOKUP(A50,'LIGIE Diciembre DOF'!$A$3:$D$1465,4,FALSE),"---") -> --- | G50: {=_xlfn.IFS(F50="---","Sin Cambios",E50=F50,"Sin Cambios",E50<>F50,"Modificado")} -> Sin Cambios
A51: 0106.90.99 | B51: Animales vivos y productos del reino animal. Animales vivos. Los demás animales vivos. Los demás. | C51: Los demás. | D51: Pza | E51: 20 | F51: =_xlfn.IFNA(VLOOKUP(A51,'LIGIE Diciembre DOF'!$A$3:$D$1465,4,FALSE),"---") -> --- | G51: {=_xlfn.IFS(F51="---","Sin Cambios",E51=F51,"Sin Cambios",E51<>F51,"Modificado")} -> Sin Cambios
A52: 0201.10.01 | B52: Animales vivos y productos del reino animal. Carne y despojos comestibles. Carne de animales de la especie bovina, fresca o refrigerada. En canales o medias canales. | C52: En canales o medias canales. | D52: Kg | E52: 20 | F52: =_xlfn.IFNA(VLOOKUP(A52,'LIGIE Diciembre DOF'!$A$3:$D$1465,4,FALSE),"---") -> --- | G52: {=_xlfn.IFS(F52="---","Sin Cambios",E52=F52,"Sin Cambios",E52<>F52,"Modificado")} -> Sin Cambios
A53: 0201.20.91 | B53: Animales vivos y productos del reino animal. Carne y despojos comestibles. Carne de animales de la especie bovina, fresca o refrigerada. Los demás cortes (trozos) sin deshuesar. | C53: Los demás cortes (trozos) sin deshuesar. | D53: Kg | E53: 20 | F53: =_xlfn.IFNA(VLOOKUP(A53,'LIGIE Diciembre DOF'!$A$3:$D$1465,4,FALSE),"---") -> --- | G53: {=_xlfn.IFS(F53="---","Sin Cambios",E53=F53,"Sin Cambios",E53<>F53,"Modificado")} -> Sin Cambios
A54: 0201.30.01 | B54: Animales vivos y productos del reino animal. Carne y despojos comestibles. Carne de animales de la especie bovina, fresca o refrigerada. Deshuesada. | C54: Deshuesada. | D54: Kg | E54: 20 | F54: =_xlfn.IFNA(VLOOKUP(A54,'LIGIE Diciembre DOF'!$A$3:$D$1465,4,FALSE),"---") -> --- | G54: {=_xlfn.IFS(F54="---","Sin Cambios",E54=F54,"Sin Cambios",E54<>F54,"Modificado")} -> Sin Cambios
A55: 0202.10.01 | B55: Animales vivos y productos del reino animal. Carne y despojos comestibles. Carne de animales de la especie bovina, congelada. En canales o medias canales. | C55: En canales o medias canales. | D55: Kg | E55: 25 | F55: =_xlfn.IFNA(VLOOKUP(A55,'LIGIE Diciembre DOF'!$A$3:$D$1465,4,FALSE),"---") -> --- | G55: {=_xlfn.IFS(F55="---","Sin Cambios",E55=F55,"Sin Cambios",E55<>F55,"Modificado")} -> Sin Cambios
A56: 0202.20.91 | B56: Animales vivos y productos del reino animal. Carne y despojos comestibles. Carne de animales de la especie bovina, congelada. Los demás cortes (trozos) sin deshuesar. | C56: Los demás cortes (trozos) sin deshuesar. | D56: Kg | E56: 25 | F56: =_xlfn.IFNA(VLOOKUP(A56,'LIGIE Diciembre DOF'!$A$3:$D$1465,4,FALSE),"---") -> --- | G56: {=_xlfn.IFS(F56="---","Sin Cambios",E56=F56,"Sin Cambios",E56<>F56,"Modificado")} -> Sin Cambios
A57: 0202.30.01 | B57: Animales vivos y productos del reino animal. Carne y despojos comestibles. Carne de animales de la especie bovina, congelada. Deshuesada. | C57: Deshuesada. | D57: Kg | E57: 25 | F57: =_xlfn.IFNA(VLOOKUP(A57,'LIGIE Diciembre DOF'!$A$3:$D$1465,4,FALSE),"---") -> --- | G57: {=_xlfn.IFS(F57="---","Sin Cambios",E57=F57,"Sin Cambios",E57<>F57,"Modificado")} -> Sin Cambios
A58: 0203.11.01 | B58: Animales vivos y productos del reino animal. Carne y despojos comestibles. Carne de animales de la especie porcina, fresca, refrigerada o congelada. Fresca o refrigerada: En canales o medias canales. | C58: En canales o medias canales. | D58: Kg | E58: 20 | F58: =_xlfn.IFNA(VLOOKUP(A58,'LIGIE Diciembre DOF'!$A$3:$D$1465,4,FALSE),"---") -> --- | G58: {=_xlfn.IFS(F58="---","Sin Cambios",E58=F58,"Sin Cambios",E58<>F58,"Modificado")} -> Sin Cambios
A59: 0203.12.01 | B59: Animales vivos y productos del reino animal. Carne y despojos comestibles. Carne de animales de la especie porcina, fresca, refrigerada o congelada. Fresca o refrigerada: Piernas, paletas, y sus trozos, sin deshuesar. | C59: Piernas, paletas, y sus trozos, sin deshuesar. | D59: Kg | E59: 20 | F59: =_xlfn.IFNA(VLOOKUP(A59,'LIGIE Diciembre DOF'!$A$3:$D$1465,4,FALSE),"---") -> --- | G59: {=_xlfn.IFS(F59="---","Sin Cambios",E59=F59,"Sin Cambios",E59<>F59,"Modificado")} -> Sin Cambios
A60: 0203.19.99 | B60: Animales vivos y productos del reino animal. Carne y despojos comestibles. Carne de animales de la especie porcina, fresca, refrigerada o congelada. Fresca o refrigerada: Las demás. | C60: Las demás. | D60: Kg | E60: 20 | F60: =_xlfn.IFNA(VLOOKUP(A60,'LIGIE Diciembre DOF'!$A$3:$D$1465,4,FALSE),"---") -> --- | G60: {=_xlfn.IFS(F60="---","Sin Cambios",E60=F60,"Sin Cambios",E60<>F60,"Modificado")} -> Sin Cambios
A61: 0203.21.01 | B61: Animales vivos y productos del reino animal. Carne y despojos comestibles. Carne de animales de la especie porcina, fresca, refrigerada o congelada. Congelada: En canales o medias canales. | C61: En canales o medias canales. | D61: Kg | E61: 20 | F61: =_xlfn.IFNA(VLOOKUP(A61,'LIGIE Diciembre DOF'!$A$3:$D$1465,4,FALSE),"---") -> --- | G61: {=_xlfn.IFS(F61="---","Sin Cambios",E61=F61,"Sin Cambios",E61<>F61,"Modificado")} -> Sin Cambios
A62: 0203.22.01 | B62: Animales vivos y productos del reino animal. Carne y despojos comestibles. Carne de animales de la especie porcina, fresca, refrigerada o congelada. Congelada: Piernas, paletas, y sus trozos, sin deshuesar. | C62: Piernas, paletas, y sus trozos, sin deshuesar. | D62: Kg | E62: 20 | F62: =_xlfn.IFNA(VLOOKUP(A62,'LIGIE Diciembre DOF'!$A$3:$D$1465,4,FALSE),"---") -> --- | G62: {=_xlfn.IFS(F62="---","Sin Cambios",E62=F62,"Sin Cambios",E62<>F62,"Modificado")} -> Sin Cambios
... A80: 0206.41.01 | B80: Animales vivos y productos del reino animal. Carne y despojos comestibles. Despojos comestibles de animales de las especies bovina, porcina, ovina, caprina, caballar, asnal o mular, frescos, refrigerados o congelados. De la especie porcina, congelados: Hígados. | C80: Hígados. | D80: Kg | E80: 10 | F80: =_xlfn.IFNA(VLOOKUP(A80,'LIGIE Diciembre DOF'!$A$3:$D$1465,4,FALSE),"---") -> --- | G80: {=_xlfn.IFS(F80="---","Sin Cambios",E80=F80,"Sin Cambios",E80<>F80,"Modificado")} -> Sin Cambios
A81: 0206.49.01 | B81: Animales vivos y productos del reino animal. Carne y despojos comestibles. Despojos comestibles de animales de las especies bovina, porcina, ovina, caprina, caballar, asnal o mular, frescos, refrigerados o congelados. De la especie porcina, congelados: Los demás. | C81: Pieles de cerdo enteras o en recortes, excepto el cuero precocido en trozos ("pellets"). | D81: Kg | E81: Ex. | F81: =_xlfn.IFNA(VLOOKUP(A81,'LIGIE Diciembre DOF'!$A$3:$D$1465,4,FALSE),"---") -> --- | G81: {=_xlfn.IFS(F81="---","Sin Cambios",E81=F81,"Sin Cambios",E81<>F81,"Modificado")} -> Sin Cambios
A82: 0206.49.99 | B82: Animales vivos y productos del reino animal. Carne y despojos comestibles. Despojos comestibles de animales de las especies bovina, porcina, ovina, caprina, caballar, asnal o mular, frescos, refrigerados o congelados. De la especie porcina, congelados: Los demás. | C82: Los demás. | D82: Kg | E82: 10 | F82: =_xlfn.IFNA(VLOOKUP(A82,'LIGIE Diciembre DOF'!$A$3:$D$1465,4,FALSE),"---") -> --- | G82: {=_xlfn.IFS(F82="---","Sin Cambios",E82=F82,"Sin Cambios",E82<>F82,"Modificado")} -> Sin Cambios
A83: 0206.80.91 | B83: Animales vivos y productos del reino animal. Carne y despojos comestibles. Despojos comestibles de animales de las especies bovina, porcina, ovina, caprina, caballar, asnal o mular, frescos, refrigerados o congelados. Los demás, frescos o refrigerados. | C83: Los demás, frescos o refrigerados. | D83: Kg | E83: 10 | F83: =_xlfn.IFNA(VLOOKUP(A83,'LIGIE Diciembre DOF'!$A$3:$D$1465,4,FALSE),"---") -> --- | G83: {=_xlfn.IFS(F83="---","Sin Cambios",E83=F83,"Sin Cambios",E83<>F83,"Modificado")} -> Sin Cambios
A84: 0206.90.91 | B84: Animales vivos y productos del reino animal. Carne y despojos comestibles. Despojos comestibles de animales de las especies bovina, porcina, ovina, caprina, caballar, asnal o mular, frescos, refrigerados o congelados. Los demás, congelados. | C84: Los demás, congelados. | D84: Kg | E84: 10 | F84: =_xlfn.IFNA(VLOOKUP(A84,'LIGIE Diciembre DOF'!$A$3:$D$1465,4,FALSE),"---") -> --- | G84: {=_xlfn.IFS(F84="---","Sin Cambios",E84=F84,"Sin Cambios",E84<>F84,"Modificado")} -> Sin Cambios
A85: 0207.11.01 | B85: Animales vivos y productos del reino animal. Carne y despojos comestibles. Carne y despojos comestibles, de aves de la partida 01.05, frescos, refrigerados o congelados. De aves de la especie Gallus domesticus: Sin trocear, frescos o refrigerados. | C85: Sin trocear, frescos o refrigerados. | D85: Kg | E85: 75 | F85: =_xlfn.IFNA(VLOOKUP(A85,'LIGIE Diciembre DOF'!$A$3:$D$1465,4,FALSE),"---") -> --- | G85: {=_xlfn.IFS(F85="---","Sin Cambios",E85=F85,"Sin Cambios",E85<>F85,"Modificado")} -> Sin Cambios
A86: 0207.12.01 | B86: Animales vivos y productos del reino animal. Carne y despojos comestibles. Carne y despojos comestibles, de aves de la partida 01.05, frescos, refrigerados o congelados. De aves de la especie Gallus domesticus: Sin trocear, congelados. | C86: Sin trocear, congelados. | D86: Kg | E86: 75 | F86: =_xlfn.IFNA(VLOOKUP(A86,'LIGIE Diciembre DOF'!$A$3:$D$1465,4,FALSE),"---") -> --- | G86: {=_xlfn.IFS(F86="---","Sin Cambios",E86=F86,"Sin Cambios",E86<>F86,"Modificado")} -> Sin Cambios
A87: 0207.13.04 | B87: Animales vivos y productos del reino animal. Carne y despojos comestibles. Carne y despojos comestibles, de aves de la partida 01.05, frescos, refrigerados o congelados. De aves de la especie Gallus domesticus: Trozos y despojos, frescos o refrigerados. | C87: Trozos y despojos, frescos o refrigerados. | D87: Kg | E87: 75 | F87: =_xlfn.IFNA(VLOOKUP(A87,'LIGIE Diciembre DOF'!$A$3:$D$1465,4,FALSE),"---") -> --- | G87: {=_xlfn.IFS(F87="---","Sin Cambios",E87=F87,"Sin Cambios",E87<>F87,"Modificado")} -> Sin Cambios
A88: 0207.14.02 | B88: Animales vivos y productos del reino animal. Carne y despojos comestibles. Carne y despojos comestibles, de aves de la partida 01.05, frescos, refrigerados o congelados. De aves de la especie Gallus domesticus: Trozos y despojos, congelados. | C88: Hígados. | D88: Kg | E88: 10 | F88: =_xlfn.IFNA(VLOOKUP(A88,'LIGIE Diciembre DOF'!$A$3:$D$1465,4,FALSE),"---") -> --- | G88: {=_xlfn.IFS(F88="---","Sin Cambios",E88=F88,"Sin Cambios",E88<>F88,"Modificado")} -> Sin Cambios
A89: 0207.14.99 | B89: Animales vivos y productos del reino animal. Carne y despojos comestibles. Carne y despojos comestibles, de aves de la partida 01.05, frescos, refrigerados o congelados. De aves de la especie Gallus domesticus: Trozos y despojos, congelados. | C89: Los demás. | D89: Kg | E89: 75 | F89: =_xlfn.IFNA(VLOOKUP(A89,'LIGIE Diciembre DOF'!$A$3:$D$1465,4,FALSE),"---") -> --- | G89: {=_xlfn.IFS(F89="---","Sin Cambios",E89=F89,"Sin Cambios",E89<>F89,"Modificado")} -> Sin Cambios
A90: 0207.24.01 | B90: Animales vivos y productos del reino animal. Carne y despojos comestibles. Carne y despojos comestibles, de aves de la partida 01.05, frescos, refrigerados o congelados. De pavo (gallipavo): Sin trocear, frescos o refrigerados. | C90: Sin trocear, frescos o refrigerados. | D90: Kg | E90: 45 | F90: =_xlfn.IFNA(VLOOKUP(A90,'LIGIE Diciembre DOF'!$A$3:$D$1465,4,FALSE),"---") -> --- | G90: {=_xlfn.IFS(F90="---","Sin Cambios",E90=F90,"Sin Cambios",E90<>F90,"Modificado")} -> Sin Cambios
A91: 0207.25.01 | B91: Animales vivos y productos del reino animal. Carne y despojos comestibles. Carne y despojos comestibles, de aves de la partida 01.05, frescos, refrigerados o congelados. De pavo (gallipavo): Sin trocear, congelados. | C91: Sin trocear, congelados. | D91: Kg | E91: 45 | F91: =_xlfn.IFNA(VLOOKUP(A91,'LIGIE Diciembre DOF'!$A$3:$D$1465,4,FALSE),"---") -> --- | G91: {=_xlfn.IFS(F91="---","Sin Cambios",E91=F91,"Sin Cambios",E91<>F91,"Modificado")} -> Sin Cambios
A92: 0207.26.03 | B92: Animales vivos y productos del reino animal. Carne y despojos comestibles. Carne y despojos comestibles, de aves de la partida 01.05, frescos, refrigerados o congelados. De pavo (gallipavo): Trozos y despojos, frescos o refrigerados. | C92: Trozos y despojos, frescos o refrigerados. | D92: Kg | E92: 75 | F92: =_xlfn.IFNA(VLOOKUP(A92,'LIGIE Diciembre DOF'!$A$3:$D$1465,4,FALSE),"---") -> --- | G92: {=_xlfn.IFS(F92="---","Sin Cambios",E92=F92,"Sin Cambios",E92<>F92,"Modificado")} -> Sin Cambios
A93: 0207.27.02 | B93: Animales vivos y productos del reino animal. Carne y despojos comestibles. Carne y despojos comestibles, de aves de la partida 01.05, frescos, refrigerados o congelados. De pavo (gallipavo): Trozos y despojos, congelados. | C93: Hígados. | D93: Kg | E93: 10 | F93: =_xlfn.IFNA(VLOOKUP(A93,'LIGIE Diciembre DOF'!$A$3:$D$1465,4,FALSE),"---") -> --- | G93: {=_xlfn.IFS(F93="---","Sin Cambios",E93=F93,"Sin Cambios",E93<>F93,"Modificado")} -> Sin Cambios
A94: 0207.27.99 | B94: Animales vivos y productos del reino animal. Carne y despojos comestibles. Carne y despojos comestibles, de aves de la partida 01.05, frescos, refrigerados o congelados. De pavo (gallipavo): Trozos y despojos, congelados. | C94: Los demás. | D94: Kg | E94: 75 | F94: =_xlfn.IFNA(VLOOKUP(A94,'LIGIE Diciembre DOF'!$A$3:$D$1465,4,FALSE),"---") -> --- | G94: {=_xlfn.IFS(F94="---","Sin Cambios",E94=F94,"Sin Cambios",E94<>F94,"Modificado")} -> Sin Cambios
A95: 0207.41.01 | B95: Animales vivos y productos del reino animal. Carne y despojos comestibles. Carne y despojos comestibles, de aves de la partida 01.05, frescos, refrigerados o congelados. De pato: Sin trocear, frescos o refrigerados. | C95: Sin trocear, frescos o refrigerados. | D95: Kg | E95: Ex. | F95: =_xlfn.IFNA(VLOOKUP(A95,'LIGIE Diciembre DOF'!$A$3:$D$1465,4,FALSE),"---") -> --- | G95: {=_xlfn.IFS(F95="---","Sin Cambios",E95=F95,"Sin Cambios",E95<>F95,"Modificado")} -> Sin Cambios
A96: 0207.42.01 | B96: Animales vivos y productos del reino animal. Carne y despojos comestibles. Carne y despojos comestibles, de aves de la partida 01.05, frescos, refrigerados o congelados. De pato: Sin trocear, congelados. | C96: Sin trocear, congelados. | D96: Kg | E96: Ex. | F96: =_xlfn.IFNA(VLOOKUP(A96,'LIGIE Diciembre DOF'!$A$3:$D$1465,4,FALSE),"---") -> --- | G96: {=_xlfn.IFS(F96="---","Sin Cambios",E96=F96,"Sin Cambios",E96<>F96,"Modificado")} -> Sin Cambios
A97: 0207.43.01 | B97: Animales vivos y productos del reino animal. Carne y despojos comestibles. Carne y despojos comestibles, de aves de la partida 01.05, frescos, refrigerados o congelados. De pato: Hígados grasos, frescos o refrigerados. | C97: Hígados grasos, frescos o refrigerados. | D97: Kg | E97: 10 | F97: =_xlfn.IFNA(VLOOKUP(A97,'LIGIE Diciembre DOF'!$A$3:$D$1465,4,FALSE),"---") -> --- | G97: {=_xlfn.IFS(F97="---","Sin Cambios",E97=F97,"Sin Cambios",E97<>F97,"Modificado")} -> Sin Cambios
A98: 0207.44.91 | B98: Animales vivos y productos del reino animal. Carne y despojos comestibles. Carne y despojos comestibles, de aves de la partida 01.05, frescos, refrigerados o congelados. De pato: Los demás, frescos o refrigerados. | C98: Los demás, frescos o refrigerados. | D98: Kg | E98: Ex. | F98: =_xlfn.IFNA(VLOOKUP(A98,'LIGIE Diciembre DOF'!$A$3:$D$1465,4,FALSE),"---") -> --- | G98: {=_xlfn.IFS(F98="---","Sin Cambios",E98=F98,"Sin Cambios",E98<>F98,"Modificado")} -> Sin Cambios
A99: 0207.45.01 | B99: Animales vivos y productos del reino animal. Carne y despojos comestibles. Carne y despojos comestibles, de aves de la partida 01.05, frescos, refrigerados o congelados. De pato: Los demás, congelados. | C99: Hígados. | D99: Kg | E99: 10 | F99: =_xlfn.IFNA(VLOOKUP(A99,'LIGIE Diciembre DOF'!$A$3:$D$1465,4,FALSE),"---") -> --- | G99: {=_xlfn.IFS(F99="---","Sin Cambios",E99=F99,"Sin Cambios",E99<>F99,"Modificado")} -> Sin Cambios
A100: 0207.45.99 | B100: Animales vivos y productos del reino animal. Carne y despojos comestibles. Carne y despojos comestibles, de aves de la partida 01.05, frescos, refrigerados o congelados. De pato: Los demás, congelados. | C100: Los demás. | D100: Kg | E100: Ex. | F100: =_xlfn.IFNA(VLOOKUP(A100,'LIGIE Diciembre DOF'!$A$3:$D$1465,4,FALSE),"---") -> --- | G100: {=_xlfn.IFS(F100="---","Sin Cambios",E100=F100,"Sin Cambios",E100<>F100,"Modificado")} -> Sin Cambios
A101: 0207.51.01 | B101: Animales vivos y productos del reino animal. Carne y despojos comestibles. Carne y despojos comestibles, de aves de la partida 01.05, frescos, refrigerados o congelados. De ganso: Sin trocear, frescos o refrigerados. | C101: Sin trocear, frescos o refrigerados. | D101: Kg | E101: Ex. | F101: =_xlfn.IFNA(VLOOKUP(A101,'LIGIE Diciembre DOF'!$A$3:$D$1465,4,FALSE),"---") -> --- | G101: {=_xlfn.IFS(F101="---","Sin Cambios",E101=F101,"Sin Cambios",E101<>F101,"Modificado")} -> Sin Cambios
A102: 0207.52.01 | B102: Animales vivos y productos del reino animal. Carne y despojos comestibles. Carne y despojos comestibles, de aves de la partida 01.05, frescos, refrigerados o congelados. De ganso: Sin trocear, congelados. | C102: Sin trocear, congelados. | D102: Kg | E102: Ex. | F102: =_xlfn.IFNA(VLOOKUP(A102,'LIGIE Diciembre DOF'!$A$3:$D$1465,4,FALSE),"---") -> --- | G102: {=_xlfn.IFS(F102="---","Sin Cambios",E102=F102,"Sin Cambios",E102<>F102,"Modificado")} -> Sin Cambios
A103: 0207.53.01 | B103: Animales vivos y productos del reino animal. Carne y despojos comestibles. Carne y despojos comestibles, de aves de la partida 01.05, frescos, refrigerados o congelados. De ganso: Hígados grasos, frescos o refrigerados. | C103: Hígados grasos, frescos o refrigerados. | D103: Kg | E103: 10 | F103: =_xlfn.IFNA(VLOOKUP(A103,'LIGIE Diciembre DOF'!$A$3:$D$1465,4,FALSE),"---") -> --- | G103: {=_xlfn.IFS(F103="---","Sin Cambios",E103=F103,"Sin Cambios",E103<>F103,"Modificado")} -> Sin Cambios
A104: 0207.54.91 | B104: Animales vivos y productos del reino animal. Carne y despojos comestibles. Carne y despojos comestibles, de aves de la partida 01.05, frescos, refrigerados o congelados. De ganso: Los demás, frescos o refrigerados. | C104: Los demás, frescos o refrigerados. | D104: Kg | E104: Ex. | F104: =_xlfn.IFNA(VLOOKUP(A104,'LIGIE Diciembre DOF'!$A$3:$D$1465,4,FALSE),"---") -> --- | G104: {=_xlfn.IFS(F104="---","Sin Cambios",E104=F104,"Sin Cambios",E104<>F104,"Modificado")} -> Sin Cambios
A105: 0207.55.01 | B105: Animales vivos y productos del reino animal. Carne y despojos comestibles. Carne y despojos comestibles, de aves de la partida 01.05, frescos, refrigerados o congelados. De ganso: Los demás, congelados. | C105: Hígados. | D105: Kg | E105: 10 | F105: =_xlfn.IFNA(VLOOKUP(A105,'LIGIE Diciembre DOF'!$A$3:$D$1465,4,FALSE),"---") -> --- | G105: {=_xlfn.IFS(F105="---","Sin Cambios",E105=F105,"Sin Cambios",E105<>F105,"Modificado")} -> Sin Cambios
A106: 0207.55.99 | B106: Animales vivos y productos del reino animal. Carne y despojos comestibles. Carne y despojos comestibles, de aves de la partida 01.05, frescos, refrigerados o congelados. De ganso: Los demás, congelados. | C106: Los demás. | D106: Kg | E106: Ex. | F106: =_xlfn.IFNA(VLOOKUP(A106,'LIGIE Diciembre DOF'!$A$3:$D$1465,4,FALSE),"---") -> --- | G106: {=_xlfn.IFS(F106="---","Sin Cambios",E106=F106,"Sin Cambios",E106<>F106,"Modificado")} -> Sin Cambios
A107: 0207.60.03 | B107: Animales vivos y productos del reino animal. Carne y despojos comestibles. Carne y despojos comestibles, de aves de la partida 01.05, frescos, refrigerados o congelados. De pintada. | C107: De pintada. | D107: Kg | E107: Ex. | F107: =_xlfn.IFNA(VLOOKUP(A107,'LIGIE Diciembre DOF'!$A$3:$D$1465,4,FALSE),"---") -> --- | G107: {=_xlfn.IFS(F107="---","Sin Cambios",E107=F107,"Sin Cambios",E107<>F107,"Modificado")} -> Sin Cambios
A108: 0208.10.01 | B108: Animales vivos y productos del reino animal. Carne y despojos comestibles. Las demás carnes y despojos comestibles, frescos, refrigerados o congelados. De conejo o liebre. | C108: De conejo o liebre. | D108: Kg | E108: 10 | F108: =_xlfn.IFNA(VLOOKUP(A108,'LIGIE Diciembre DOF'!$A$3:$D$1465,4,FALSE),"---") -> --- | G108: {=_xlfn.IFS(F108="---","Sin Cambios",E108=F108,"Sin Cambios",E108<>F108,"Modificado")} -> Sin Cambios
A109: 0208.30.01 | B109: Animales vivos y productos del reino animal. Carne y despojos comestibles. Las demás carnes y despojos comestibles, frescos, refrigerados o congelados. De primates. | C109: De primates. | D109: Kg | E109: 10 | F109: =_xlfn.IFNA(VLOOKUP(A109,'LIGIE Diciembre DOF'!$A$3:$D$1465,4,FALSE),"---") -> --- | G109: {=_xlfn.IFS(F109="---","Sin Cambios",E109=F109,"Sin Cambios",E109<>F109,"Modificado")} -> Sin Cambios
A110: 0208.40.01 | B110: Animales vivos y productos del reino animal. Carne y despojos comestibles. Las demás carnes y despojos comestibles, frescos, refrigerados o congelados. De ballenas, delfines y marsopas (mamíferos del orden Cetacea); de manatíes y dugones o dugongos (mamíferos del orden Sirenia); de otarios y focas, leones marinos y morsas (mamíferos del suborden Pinnipedia). | C110: De ballenas, delfines y marsopas (mamíferos del orden Cetacea); de manatíes y dugones o dugongos (mamíferos del orden Sirenia); de otarios y focas, leones marinos y morsas (mamíferos del suborden Pinnipedia). | D110: Kg | E110: 10 | F110: =_xlfn.IFNA(VLOOKUP(A110,'LIGIE Diciembre DOF'!$A$3:$D$1465,4,FALSE),"---") -> --- | G110: {=_xlfn.IFS(F110="---","Sin Cambios",E110=F110,"Sin Cambios",E110<>F110,"Modificado")} -> Sin Cambios
A111: 0208.50.01 | B111: Animales vivos y productos del reino animal. Carne y despojos comestibles. Las demás carnes y despojos comestibles, frescos, refrigerados o congelados. De reptiles (incluidas las serpientes y tortugas de mar). | C111: De reptiles (incluidas las serpientes y tortugas de mar). | D111: Kg | E111: 10 | F111: =_xlfn.IFNA(VLOOKUP(A111,'LIGIE Diciembre DOF'!$A$3:$D$1465,4,FALSE),"---") -> --- | G111: {=_xlfn.IFS(F111="---","Sin Cambios",E111=F111,"Sin Cambios",E111<>F111,"Modificado")} -> Sin Cambios
A112: 0208.60.01 | B112: Animales vivos y productos del reino animal. Carne y despojos comestibles. Las demás carnes y despojos comestibles, frescos, refrigerados o congelados. De camellos y demás camélidos (Camelidae). | C112: De camellos y demás camélidos (Camelidae). | D112: Kg | E112: 10 | F112: =_xlfn.IFNA(VLOOKUP(A112,'LIGIE Diciembre DOF'!$A$3:$D$1465,4,FALSE),"---") -> --- | G112: {=_xlfn.IFS(F112="---","Sin Cambios",E112=F112,"Sin Cambios",E112<>F112,"Modificado")} -> Sin Cambios
A113: 0208.90.99 | B113: Animales vivos y productos del reino animal. Carne y despojos comestibles. Las demás carnes y despojos comestibles, frescos, refrigerados o congelados. Los demás. | C113: Los demás. | D113: Kg | E113: 10 | F113: =_xlfn.IFNA(VLOOKUP(A113,'LIGIE Diciembre DOF'!$A$3:$D$1465,4,FALSE),"---") -> --- | G113: {=_xlfn.IFS(F113="---","Sin Cambios",E113=F113,"Sin Cambios",E113<>F113,"Modificado")} -> Sin Cambios
A114: 0209.10.01 | B114: Animales vivos y productos del reino animal. Carne y despojos comestibles. Tocino sin partes magras y grasa de cerdo o de ave sin fundir ni extraer de otro modo, frescos, refrigerados, congelados, salados o en salmuera, secos o ahumados. De cerdo. | C114: De cerdo. | D114: Kg | E114: 15 | F114: =_xlfn.IFNA(VLOOKUP(A114,'LIGIE Diciembre DOF'!$A$3:$D$1465,4,FALSE),"---") -> --- | G114: {=_xlfn.IFS(F114="---","Sin Cambios",E114=F114,"Sin Cambios",E114<>F114,"Modificado")} -> Sin Cambios
A115: 0209.90.01 | B115: Animales vivos y productos del reino animal. Carne y despojos comestibles. Tocino sin partes magras y grasa de cerdo o de ave sin fundir ni extraer de otro modo, frescos, refrigerados, congelados, salados o en salmuera, secos o ahumados. Los demás. | C115: De gallo, gallina o pavo (gallipavo). | D115: Kg | E115: Ex. | F115: =_xlfn.IFNA(VLOOKUP(A115,'LIGIE Diciembre DOF'!$A$3:$D$1465,4,FALSE),"---") -> --- | G115: {=_xlfn.IFS(F115="---","Sin Cambios",E115=F115,"Sin Cambios",E115<>F115,"Modificado")} -> Sin Cambios
A116: 0209.90.99 | B116: Animales vivos y productos del reino animal. Carne y despojos comestibles. Tocino sin partes magras y grasa de cerdo o de ave sin fundir ni extraer de otro modo, frescos, refrigerados, congelados, salados o en salmuera, secos o ahumados. Los demás. | C116: Los demás. | D116: Kg | E116: 15 | F116: =_xlfn.IFNA(VLOOKUP(A116,'LIGIE Diciembre DOF'!$A$3:$D$1465,4,FALSE),"---") -> --- | G116: {=_xlfn.IFS(F116="---","Sin Cambios",E116=F116,"Sin Cambios",E116<>F116,"Modificado")} -> Sin Cambios
A117: 0210.11.01 | B117: Animales vivos y productos del reino animal. Carne y despojos comestibles. Carne y despojos comestibles, salados o en salmuera, secos o ahumados; harina y polvo comestibles, de carne o de despojos. Carne de la especie porcina: Jamones, paletas, y sus trozos, sin deshuesar. | C117: Jamones, paletas, y sus trozos, sin deshuesar. | D117: Kg | E117: 10 | F117: =_xlfn.IFNA(VLOOKUP(A117,'LIGIE Diciembre DOF'!$A$3:$D$1465,4,FALSE),"---") -> --- | G117: {=_xlfn.IFS(F117="---","Sin Cambios",E117=F117,"Sin Cambios",E117<>F117,"Modificado")} -> Sin Cambios
...
